{"nodes": [{"id": "c_users_allio_desktop_runique_runique_src_utils_mod_rs", "label": "mod.rs", "file_type": "code", "source_file": "C:\\Users\\allio\\Desktop\\runique\\runique\\src\\utils\\mod.rs", "source_location": "L1"}], "edges": [{"source": "c_users_allio_desktop_runique_runique_src_utils_mod_rs", "target": "aliases", "relation": "imports_from", "confidence": "EXTRACTED", "source_file": "C:\\Users\\allio\\Desktop\\runique\\runique\\src\\utils\\mod.rs", "source_location": "L16", "weight": 1.0}, {"source": "c_users_allio_desktop_runique_runique_src_utils_mod_rs", "target": "create_new_project", "relation": "imports_from", "confidence": "EXTRACTED", "source_file": "C:\\Users\\allio\\Desktop\\runique\\runique\\src\\utils\\mod.rs", "source_location": "L17", "weight": 1.0}, {"source": "c_users_allio_desktop_runique_runique_src_utils_mod_rs", "target": "config", "relation": "imports_from", "confidence": "EXTRACTED", "source_file": "C:\\Users\\allio\\Desktop\\runique\\runique\\src\\utils\\mod.rs", "source_location": "L18", "weight": 1.0}, {"source": "c_users_allio_desktop_runique_runique_src_utils_mod_rs", "target": "constante", "relation": "imports_from", "confidence": "EXTRACTED", "source_file": "C:\\Users\\allio\\Desktop\\runique\\runique\\src\\utils\\mod.rs", "source_location": "L19", "weight": 1.0}, {"source": "c_users_allio_desktop_runique_runique_src_utils_mod_rs", "target": "is_debug", "relation": "imports_from", "confidence": "EXTRACTED", "source_file": "C:\\Users\\allio\\Desktop\\runique\\runique\\src\\utils\\mod.rs", "source_location": "L20", "weight": 1.0}, {"source": "c_users_allio_desktop_runique_runique_src_utils_mod_rs", "target": "forms", "relation": "imports_from", "confidence": "EXTRACTED", "source_file": "C:\\Users\\allio\\Desktop\\runique\\runique\\src\\utils\\mod.rs", "source_location": "L21", "weight": 1.0}, {"source": "c_users_allio_desktop_runique_runique_src_utils_mod_rs", "target": "init_logging", "relation": "imports_from", "confidence": "EXTRACTED", "source_file": "C:\\Users\\allio\\Desktop\\runique\\runique\\src\\utils\\mod.rs", "source_location": "L22", "weight": 1.0}, {"source": "c_users_allio_desktop_runique_runique_src_utils_mod_rs", "target": "mailer", "relation": "imports_from", "confidence": "EXTRACTED", "source_file": "C:\\Users\\allio\\Desktop\\runique\\runique\\src\\utils\\mod.rs", "source_location": "L23", "weight": 1.0}, {"source": "c_users_allio_desktop_runique_runique_src_utils_mod_rs", "target": "middleware", "relation": "imports_from", "confidence": "EXTRACTED", "source_file": "C:\\Users\\allio\\Desktop\\runique\\runique\\src\\utils\\mod.rs", "source_location": "L24", "weight": 1.0}, {"source": "c_users_allio_desktop_runique_runique_src_utils_mod_rs", "target": "password", "relation": "imports_from", "confidence": "EXTRACTED", "source_file": "C:\\Users\\allio\\Desktop\\runique\\runique\\src\\utils\\mod.rs", "source_location": "L25", "weight": 1.0}, {"source": "c_users_allio_desktop_runique_runique_src_utils_mod_rs", "target": "pk", "relation": "imports_from", "confidence": "EXTRACTED", "source_file": "C:\\Users\\allio\\Desktop\\runique\\runique\\src\\utils\\mod.rs", "source_location": "L26", "weight": 1.0}, {"source": "c_users_allio_desktop_runique_runique_src_utils_mod_rs", "target": "resolve_og_image", "relation": "imports_from", "confidence": "EXTRACTED", "source_file": "C:\\Users\\allio\\Desktop\\runique\\runique\\src\\utils\\mod.rs", "source_location": "L27", "weight": 1.0}], "raw_calls": []}