{"nodes": [{"id": "c_users_allio_desktop_runique_runique_tests_migration_test_column_def_extra_rs", "label": "test_column_def_extra.rs", "file_type": "code", "source_file": "C:\\Users\\allio\\Desktop\\runique\\runique\\tests\\migration\\test_column_def_extra.rs", "source_location": "L1"}, {"id": "test_column_def_extra_test_column_inet", "label": "test_column_inet()", "file_type": "code", "source_file": "C:\\Users\\allio\\Desktop\\runique\\runique\\tests\\migration\\test_column_def_extra.rs", "source_location": "L13"}, {"id": "test_column_def_extra_test_column_cidr", "label": "test_column_cidr()", "file_type": "code", "source_file": "C:\\Users\\allio\\Desktop\\runique\\runique\\tests\\migration\\test_column_def_extra.rs", "source_location": "L19"}, {"id": "test_column_def_extra_test_column_mac_address", "label": "test_column_mac_address()", "file_type": "code", "source_file": "C:\\Users\\allio\\Desktop\\runique\\runique\\tests\\migration\\test_column_def_extra.rs", "source_location": "L25"}, {"id": "test_column_def_extra_test_column_interval", "label": "test_column_interval()", "file_type": "code", "source_file": "C:\\Users\\allio\\Desktop\\runique\\runique\\tests\\migration\\test_column_def_extra.rs", "source_location": "L31"}, {"id": "test_column_def_extra_test_column_char", "label": "test_column_char()", "file_type": "code", "source_file": "C:\\Users\\allio\\Desktop\\runique\\runique\\tests\\migration\\test_column_def_extra.rs", "source_location": "L41"}, {"id": "test_column_def_extra_test_column_char_len", "label": "test_column_char_len()", "file_type": "code", "source_file": "C:\\Users\\allio\\Desktop\\runique\\runique\\tests\\migration\\test_column_def_extra.rs", "source_location": "L47"}, {"id": "test_column_def_extra_test_column_var_binary", "label": "test_column_var_binary()", "file_type": "code", "source_file": "C:\\Users\\allio\\Desktop\\runique\\runique\\tests\\migration\\test_column_def_extra.rs", "source_location": "L53"}, {"id": "test_column_def_extra_test_column_blob", "label": "test_column_blob()", "file_type": "code", "source_file": "C:\\Users\\allio\\Desktop\\runique\\runique\\tests\\migration\\test_column_def_extra.rs", "source_location": "L59"}, {"id": "test_column_def_extra_test_column_unsigned", "label": "test_column_unsigned()", "file_type": "code", "source_file": "C:\\Users\\allio\\Desktop\\runique\\runique\\tests\\migration\\test_column_def_extra.rs", "source_location": "L65"}, {"id": "test_column_def_extra_test_column_big_unsigned", "label": "test_column_big_unsigned()", "file_type": "code", "source_file": "C:\\Users\\allio\\Desktop\\runique\\runique\\tests\\migration\\test_column_def_extra.rs", "source_location": "L71"}, {"id": "test_column_def_extra_test_to_sea_column_avec_default", "label": "test_to_sea_column_avec_default()", "file_type": "code", "source_file": "C:\\Users\\allio\\Desktop\\runique\\runique\\tests\\migration\\test_column_def_extra.rs", "source_location": "L81"}, {"id": "test_column_def_extra_test_to_sea_column_nullable", "label": "test_to_sea_column_nullable()", "file_type": "code", "source_file": "C:\\Users\\allio\\Desktop\\runique\\runique\\tests\\migration\\test_column_def_extra.rs", "source_location": "L89"}, {"id": "test_column_def_extra_test_to_sea_column_unique", "label": "test_to_sea_column_unique()", "file_type": "code", "source_file": "C:\\Users\\allio\\Desktop\\runique\\runique\\tests\\migration\\test_column_def_extra.rs", "source_location": "L95"}, {"id": "test_column_def_extra_test_to_form_field_password_name", "label": "test_to_form_field_password_name()", "file_type": "code", "source_file": "C:\\Users\\allio\\Desktop\\runique\\runique\\tests\\migration\\test_column_def_extra.rs", "source_location": "L105"}, {"id": "test_column_def_extra_test_to_form_field_password_suffixe", "label": "test_to_form_field_password_suffixe()", "file_type": "code", "source_file": "C:\\Users\\allio\\Desktop\\runique\\runique\\tests\\migration\\test_column_def_extra.rs", "source_location": "L111"}, {"id": "test_column_def_extra_test_to_form_field_url_name", "label": "test_to_form_field_url_name()", "file_type": "code", "source_file": "C:\\Users\\allio\\Desktop\\runique\\runique\\tests\\migration\\test_column_def_extra.rs", "source_location": "L117"}, {"id": "test_column_def_extra_test_to_form_field_website_name", "label": "test_to_form_field_website_name()", "file_type": "code", "source_file": "C:\\Users\\allio\\Desktop\\runique\\runique\\tests\\migration\\test_column_def_extra.rs", "source_location": "L123"}, {"id": "test_column_def_extra_test_to_form_field_slug_name", "label": "test_to_form_field_slug_name()", "file_type": "code", "source_file": "C:\\Users\\allio\\Desktop\\runique\\runique\\tests\\migration\\test_column_def_extra.rs", "source_location": "L129"}, {"id": "test_column_def_extra_test_to_form_field_color_name", "label": "test_to_form_field_color_name()", "file_type": "code", "source_file": "C:\\Users\\allio\\Desktop\\runique\\runique\\tests\\migration\\test_column_def_extra.rs", "source_location": "L135"}, {"id": "test_column_def_extra_test_to_form_field_ip_name", "label": "test_to_form_field_ip_name()", "file_type": "code", "source_file": "C:\\Users\\allio\\Desktop\\runique\\runique\\tests\\migration\\test_column_def_extra.rs", "source_location": "L141"}, {"id": "test_column_def_extra_test_to_form_field_text_description", "label": "test_to_form_field_text_description()", "file_type": "code", "source_file": "C:\\Users\\allio\\Desktop\\runique\\runique\\tests\\migration\\test_column_def_extra.rs", "source_location": "L147"}, {"id": "test_column_def_extra_test_to_form_field_text_bio", "label": "test_to_form_field_text_bio()", "file_type": "code", "source_file": "C:\\Users\\allio\\Desktop\\runique\\runique\\tests\\migration\\test_column_def_extra.rs", "source_location": "L153"}, {"id": "test_column_def_extra_test_to_form_field_text_content", "label": "test_to_form_field_text_content()", "file_type": "code", "source_file": "C:\\Users\\allio\\Desktop\\runique\\runique\\tests\\migration\\test_column_def_extra.rs", "source_location": "L159"}, {"id": "test_column_def_extra_test_to_form_field_text_generic", "label": "test_to_form_field_text_generic()", "file_type": "code", "source_file": "C:\\Users\\allio\\Desktop\\runique\\runique\\tests\\migration\\test_column_def_extra.rs", "source_location": "L165"}, {"id": "test_column_def_extra_test_to_form_field_big_integer", "label": "test_to_form_field_big_integer()", "file_type": "code", "source_file": "C:\\Users\\allio\\Desktop\\runique\\runique\\tests\\migration\\test_column_def_extra.rs", "source_location": "L171"}, {"id": "test_column_def_extra_test_to_form_field_tiny_integer", "label": "test_to_form_field_tiny_integer()", "file_type": "code", "source_file": "C:\\Users\\allio\\Desktop\\runique\\runique\\tests\\migration\\test_column_def_extra.rs", "source_location": "L177"}, {"id": "test_column_def_extra_test_to_form_field_float", "label": "test_to_form_field_float()", "file_type": "code", "source_file": "C:\\Users\\allio\\Desktop\\runique\\runique\\tests\\migration\\test_column_def_extra.rs", "source_location": "L183"}, {"id": "test_column_def_extra_test_to_form_field_double", "label": "test_to_form_field_double()", "file_type": "code", "source_file": "C:\\Users\\allio\\Desktop\\runique\\runique\\tests\\migration\\test_column_def_extra.rs", "source_location": "L189"}, {"id": "test_column_def_extra_test_to_form_field_decimal", "label": "test_to_form_field_decimal()", "file_type": "code", "source_file": "C:\\Users\\allio\\Desktop\\runique\\runique\\tests\\migration\\test_column_def_extra.rs", "source_location": "L195"}, {"id": "test_column_def_extra_test_to_form_field_date", "label": "test_to_form_field_date()", "file_type": "code", "source_file": "C:\\Users\\allio\\Desktop\\runique\\runique\\tests\\migration\\test_column_def_extra.rs", "source_location": "L201"}, {"id": "test_column_def_extra_test_to_form_field_time", "label": "test_to_form_field_time()", "file_type": "code", "source_file": "C:\\Users\\allio\\Desktop\\runique\\runique\\tests\\migration\\test_column_def_extra.rs", "source_location": "L207"}, {"id": "test_column_def_extra_test_to_form_field_datetime", "label": "test_to_form_field_datetime()", "file_type": "code", "source_file": "C:\\Users\\allio\\Desktop\\runique\\runique\\tests\\migration\\test_column_def_extra.rs", "source_location": "L213"}, {"id": "test_column_def_extra_test_to_form_field_timestamp", "label": "test_to_form_field_timestamp()", "file_type": "code", "source_file": "C:\\Users\\allio\\Desktop\\runique\\runique\\tests\\migration\\test_column_def_extra.rs", "source_location": "L219"}, {"id": "test_column_def_extra_test_to_form_field_json_binary", "label": "test_to_form_field_json_binary()", "file_type": "code", "source_file": "C:\\Users\\allio\\Desktop\\runique\\runique\\tests\\migration\\test_column_def_extra.rs", "source_location": "L225"}, {"id": "test_column_def_extra_test_to_form_field_char", "label": "test_to_form_field_char()", "file_type": "code", "source_file": "C:\\Users\\allio\\Desktop\\runique\\runique\\tests\\migration\\test_column_def_extra.rs", "source_location": "L231"}, {"id": "test_column_def_extra_test_to_form_field_enum", "label": "test_to_form_field_enum()", "file_type": "code", "source_file": "C:\\Users\\allio\\Desktop\\runique\\runique\\tests\\migration\\test_column_def_extra.rs", "source_location": "L237"}, {"id": "test_column_def_extra_test_to_form_field_string_avec_max_len", "label": "test_to_form_field_string_avec_max_len()", "file_type": "code", "source_file": "C:\\Users\\allio\\Desktop\\runique\\runique\\tests\\migration\\test_column_def_extra.rs", "source_location": "L246"}, {"id": "test_column_def_extra_test_to_form_field_email_avec_max_len", "label": "test_to_form_field_email_avec_max_len()", "file_type": "code", "source_file": "C:\\Users\\allio\\Desktop\\runique\\runique\\tests\\migration\\test_column_def_extra.rs", "source_location": "L252"}, {"id": "test_column_def_extra_test_to_form_field_required_quand_non_nullable", "label": "test_to_form_field_required_quand_non_nullable()", "file_type": "code", "source_file": "C:\\Users\\allio\\Desktop\\runique\\runique\\tests\\migration\\test_column_def_extra.rs", "source_location": "L258"}, {"id": "test_column_def_extra_test_to_form_field_optionnel_quand_nullable", "label": "test_to_form_field_optionnel_quand_nullable()", "file_type": "code", "source_file": "C:\\Users\\allio\\Desktop\\runique\\runique\\tests\\migration\\test_column_def_extra.rs", "source_location": "L266"}, {"id": "test_column_def_extra_test_format_label_simple", "label": "test_format_label_simple()", "file_type": "code", "source_file": "C:\\Users\\allio\\Desktop\\runique\\runique\\tests\\migration\\test_column_def_extra.rs", "source_location": "L277"}, {"id": "test_column_def_extra_test_format_label_snake_case", "label": "test_format_label_snake_case()", "file_type": "code", "source_file": "C:\\Users\\allio\\Desktop\\runique\\runique\\tests\\migration\\test_column_def_extra.rs", "source_location": "L286"}, {"id": "test_column_def_extra_test_format_label_triple", "label": "test_format_label_triple()", "file_type": "code", "source_file": "C:\\Users\\allio\\Desktop\\runique\\runique\\tests\\migration\\test_column_def_extra.rs", "source_location": "L295"}], "edges": [{"source": "c_users_allio_desktop_runique_runique_tests_migration_test_column_def_extra_rs", "target": "formfield", "relation": "imports_from", "confidence": "EXTRACTED", "source_file": "C:\\Users\\allio\\Desktop\\runique\\runique\\tests\\migration\\test_column_def_extra.rs", "source_location": "L5", "weight": 1.0}, {"source": "c_users_allio_desktop_runique_runique_tests_migration_test_column_def_extra_rs", "target": "columndef", "relation": "imports_from", "confidence": "EXTRACTED", "source_file": "C:\\Users\\allio\\Desktop\\runique\\runique\\tests\\migration\\test_column_def_extra.rs", "source_location": "L6", "weight": 1.0}, {"source": "c_users_allio_desktop_runique_runique_tests_migration_test_column_def_extra_rs", "target": "columntype", "relation": "imports_from", "confidence": "EXTRACTED", "source_file": "C:\\Users\\allio\\Desktop\\runique\\runique\\tests\\migration\\test_column_def_extra.rs", "source_location": "L7", "weight": 1.0}, {"source": "c_users_allio_desktop_runique_runique_tests_migration_test_column_def_extra_rs", "target": "test_column_def_extra_test_column_inet", "relation": "contains", "confidence": "EXTRACTED", "source_file": "C:\\Users\\allio\\Desktop\\runique\\runique\\tests\\migration\\test_column_def_extra.rs", "source_location": "L13", "weight": 1.0}, {"source": "c_users_allio_desktop_runique_runique_tests_migration_test_column_def_extra_rs", "target": "test_column_def_extra_test_column_cidr", "relation": "contains", "confidence": "EXTRACTED", "source_file": "C:\\Users\\allio\\Desktop\\runique\\runique\\tests\\migration\\test_column_def_extra.rs", "source_location": "L19", "weight": 1.0}, {"source": "c_users_allio_desktop_runique_runique_tests_migration_test_column_def_extra_rs", "target": "test_column_def_extra_test_column_mac_address", "relation": "contains", "confidence": "EXTRACTED", "source_file": "C:\\Users\\allio\\Desktop\\runique\\runique\\tests\\migration\\test_column_def_extra.rs", "source_location": "L25", "weight": 1.0}, {"source": "c_users_allio_desktop_runique_runique_tests_migration_test_column_def_extra_rs", "target": "test_column_def_extra_test_column_interval", "relation": "contains", "confidence": "EXTRACTED", "source_file": "C:\\Users\\allio\\Desktop\\runique\\runique\\tests\\migration\\test_column_def_extra.rs", "source_location": "L31", "weight": 1.0}, {"source": "c_users_allio_desktop_runique_runique_tests_migration_test_column_def_extra_rs", "target": "test_column_def_extra_test_column_char", "relation": "contains", "confidence": "EXTRACTED", "source_file": "C:\\Users\\allio\\Desktop\\runique\\runique\\tests\\migration\\test_column_def_extra.rs", "source_location": "L41", "weight": 1.0}, {"source": "c_users_allio_desktop_runique_runique_tests_migration_test_column_def_extra_rs", "target": "test_column_def_extra_test_column_char_len", "relation": "contains", "confidence": "EXTRACTED", "source_file": "C:\\Users\\allio\\Desktop\\runique\\runique\\tests\\migration\\test_column_def_extra.rs", "source_location": "L47", "weight": 1.0}, {"source": "c_users_allio_desktop_runique_runique_tests_migration_test_column_def_extra_rs", "target": "test_column_def_extra_test_column_var_binary", "relation": "contains", "confidence": "EXTRACTED", "source_file": "C:\\Users\\allio\\Desktop\\runique\\runique\\tests\\migration\\test_column_def_extra.rs", "source_location": "L53", "weight": 1.0}, {"source": "c_users_allio_desktop_runique_runique_tests_migration_test_column_def_extra_rs", "target": "test_column_def_extra_test_column_blob", "relation": "contains", "confidence": "EXTRACTED", "source_file": "C:\\Users\\allio\\Desktop\\runique\\runique\\tests\\migration\\test_column_def_extra.rs", "source_location": "L59", "weight": 1.0}, {"source": "c_users_allio_desktop_runique_runique_tests_migration_test_column_def_extra_rs", "target": "test_column_def_extra_test_column_unsigned", "relation": "contains", "confidence": "EXTRACTED", "source_file": "C:\\Users\\allio\\Desktop\\runique\\runique\\tests\\migration\\test_column_def_extra.rs", "source_location": "L65", "weight": 1.0}, {"source": "c_users_allio_desktop_runique_runique_tests_migration_test_column_def_extra_rs", "target": "test_column_def_extra_test_column_big_unsigned", "relation": "contains", "confidence": "EXTRACTED", "source_file": "C:\\Users\\allio\\Desktop\\runique\\runique\\tests\\migration\\test_column_def_extra.rs", "source_location": "L71", "weight": 1.0}, {"source": "c_users_allio_desktop_runique_runique_tests_migration_test_column_def_extra_rs", "target": "test_column_def_extra_test_to_sea_column_avec_default", "relation": "contains", "confidence": "EXTRACTED", "source_file": "C:\\Users\\allio\\Desktop\\runique\\runique\\tests\\migration\\test_column_def_extra.rs", "source_location": "L81", "weight": 1.0}, {"source": "c_users_allio_desktop_runique_runique_tests_migration_test_column_def_extra_rs", "target": "test_column_def_extra_test_to_sea_column_nullable", "relation": "contains", "confidence": "EXTRACTED", "source_file": "C:\\Users\\allio\\Desktop\\runique\\runique\\tests\\migration\\test_column_def_extra.rs", "source_location": "L89", "weight": 1.0}, {"source": "c_users_allio_desktop_runique_runique_tests_migration_test_column_def_extra_rs", "target": "test_column_def_extra_test_to_sea_column_unique", "relation": "contains", "confidence": "EXTRACTED", "source_file": "C:\\Users\\allio\\Desktop\\runique\\runique\\tests\\migration\\test_column_def_extra.rs", "source_location": "L95", "weight": 1.0}, {"source": "c_users_allio_desktop_runique_runique_tests_migration_test_column_def_extra_rs", "target": "test_column_def_extra_test_to_form_field_password_name", "relation": "contains", "confidence": "EXTRACTED", "source_file": "C:\\Users\\allio\\Desktop\\runique\\runique\\tests\\migration\\test_column_def_extra.rs", "source_location": "L105", "weight": 1.0}, {"source": "c_users_allio_desktop_runique_runique_tests_migration_test_column_def_extra_rs", "target": "test_column_def_extra_test_to_form_field_password_suffixe", "relation": "contains", "confidence": "EXTRACTED", "source_file": "C:\\Users\\allio\\Desktop\\runique\\runique\\tests\\migration\\test_column_def_extra.rs", "source_location": "L111", "weight": 1.0}, {"source": "c_users_allio_desktop_runique_runique_tests_migration_test_column_def_extra_rs", "target": "test_column_def_extra_test_to_form_field_url_name", "relation": "contains", "confidence": "EXTRACTED", "source_file": "C:\\Users\\allio\\Desktop\\runique\\runique\\tests\\migration\\test_column_def_extra.rs", "source_location": "L117", "weight": 1.0}, {"source": "c_users_allio_desktop_runique_runique_tests_migration_test_column_def_extra_rs", "target": "test_column_def_extra_test_to_form_field_website_name", "relation": "contains", "confidence": "EXTRACTED", "source_file": "C:\\Users\\allio\\Desktop\\runique\\runique\\tests\\migration\\test_column_def_extra.rs", "source_location": "L123", "weight": 1.0}, {"source": "c_users_allio_desktop_runique_runique_tests_migration_test_column_def_extra_rs", "target": "test_column_def_extra_test_to_form_field_slug_name", "relation": "contains", "confidence": "EXTRACTED", "source_file": "C:\\Users\\allio\\Desktop\\runique\\runique\\tests\\migration\\test_column_def_extra.rs", "source_location": "L129", "weight": 1.0}, {"source": "c_users_allio_desktop_runique_runique_tests_migration_test_column_def_extra_rs", "target": "test_column_def_extra_test_to_form_field_color_name", "relation": "contains", "confidence": "EXTRACTED", "source_file": "C:\\Users\\allio\\Desktop\\runique\\runique\\tests\\migration\\test_column_def_extra.rs", "source_location": "L135", "weight": 1.0}, {"source": "c_users_allio_desktop_runique_runique_tests_migration_test_column_def_extra_rs", "target": "test_column_def_extra_test_to_form_field_ip_name", "relation": "contains", "confidence": "EXTRACTED", "source_file": "C:\\Users\\allio\\Desktop\\runique\\runique\\tests\\migration\\test_column_def_extra.rs", "source_location": "L141", "weight": 1.0}, {"source": "c_users_allio_desktop_runique_runique_tests_migration_test_column_def_extra_rs", "target": "test_column_def_extra_test_to_form_field_text_description", "relation": "contains", "confidence": "EXTRACTED", "source_file": "C:\\Users\\allio\\Desktop\\runique\\runique\\tests\\migration\\test_column_def_extra.rs", "source_location": "L147", "weight": 1.0}, {"source": "c_users_allio_desktop_runique_runique_tests_migration_test_column_def_extra_rs", "target": "test_column_def_extra_test_to_form_field_text_bio", "relation": "contains", "confidence": "EXTRACTED", "source_file": "C:\\Users\\allio\\Desktop\\runique\\runique\\tests\\migration\\test_column_def_extra.rs", "source_location": "L153", "weight": 1.0}, {"source": "c_users_allio_desktop_runique_runique_tests_migration_test_column_def_extra_rs", "target": "test_column_def_extra_test_to_form_field_text_content", "relation": "contains", "confidence": "EXTRACTED", "source_file": "C:\\Users\\allio\\Desktop\\runique\\runique\\tests\\migration\\test_column_def_extra.rs", "source_location": "L159", "weight": 1.0}, {"source": "c_users_allio_desktop_runique_runique_tests_migration_test_column_def_extra_rs", "target": "test_column_def_extra_test_to_form_field_text_generic", "relation": "contains", "confidence": "EXTRACTED", "source_file": "C:\\Users\\allio\\Desktop\\runique\\runique\\tests\\migration\\test_column_def_extra.rs", "source_location": "L165", "weight": 1.0}, {"source": "c_users_allio_desktop_runique_runique_tests_migration_test_column_def_extra_rs", "target": "test_column_def_extra_test_to_form_field_big_integer", "relation": "contains", "confidence": "EXTRACTED", "source_file": "C:\\Users\\allio\\Desktop\\runique\\runique\\tests\\migration\\test_column_def_extra.rs", "source_location": "L171", "weight": 1.0}, {"source": "c_users_allio_desktop_runique_runique_tests_migration_test_column_def_extra_rs", "target": "test_column_def_extra_test_to_form_field_tiny_integer", "relation": "contains", "confidence": "EXTRACTED", "source_file": "C:\\Users\\allio\\Desktop\\runique\\runique\\tests\\migration\\test_column_def_extra.rs", "source_location": "L177", "weight": 1.0}, {"source": "c_users_allio_desktop_runique_runique_tests_migration_test_column_def_extra_rs", "target": "test_column_def_extra_test_to_form_field_float", "relation": "contains", "confidence": "EXTRACTED", "source_file": "C:\\Users\\allio\\Desktop\\runique\\runique\\tests\\migration\\test_column_def_extra.rs", "source_location": "L183", "weight": 1.0}, {"source": "c_users_allio_desktop_runique_runique_tests_migration_test_column_def_extra_rs", "target": "test_column_def_extra_test_to_form_field_double", "relation": "contains", "confidence": "EXTRACTED", "source_file": "C:\\Users\\allio\\Desktop\\runique\\runique\\tests\\migration\\test_column_def_extra.rs", "source_location": "L189", "weight": 1.0}, {"source": "c_users_allio_desktop_runique_runique_tests_migration_test_column_def_extra_rs", "target": "test_column_def_extra_test_to_form_field_decimal", "relation": "contains", "confidence": "EXTRACTED", "source_file": "C:\\Users\\allio\\Desktop\\runique\\runique\\tests\\migration\\test_column_def_extra.rs", "source_location": "L195", "weight": 1.0}, {"source": "c_users_allio_desktop_runique_runique_tests_migration_test_column_def_extra_rs", "target": "test_column_def_extra_test_to_form_field_date", "relation": "contains", "confidence": "EXTRACTED", "source_file": "C:\\Users\\allio\\Desktop\\runique\\runique\\tests\\migration\\test_column_def_extra.rs", "source_location": "L201", "weight": 1.0}, {"source": "c_users_allio_desktop_runique_runique_tests_migration_test_column_def_extra_rs", "target": "test_column_def_extra_test_to_form_field_time", "relation": "contains", "confidence": "EXTRACTED", "source_file": "C:\\Users\\allio\\Desktop\\runique\\runique\\tests\\migration\\test_column_def_extra.rs", "source_location": "L207", "weight": 1.0}, {"source": "c_users_allio_desktop_runique_runique_tests_migration_test_column_def_extra_rs", "target": "test_column_def_extra_test_to_form_field_datetime", "relation": "contains", "confidence": "EXTRACTED", "source_file": "C:\\Users\\allio\\Desktop\\runique\\runique\\tests\\migration\\test_column_def_extra.rs", "source_location": "L213", "weight": 1.0}, {"source": "c_users_allio_desktop_runique_runique_tests_migration_test_column_def_extra_rs", "target": "test_column_def_extra_test_to_form_field_timestamp", "relation": "contains", "confidence": "EXTRACTED", "source_file": "C:\\Users\\allio\\Desktop\\runique\\runique\\tests\\migration\\test_column_def_extra.rs", "source_location": "L219", "weight": 1.0}, {"source": "c_users_allio_desktop_runique_runique_tests_migration_test_column_def_extra_rs", "target": "test_column_def_extra_test_to_form_field_json_binary", "relation": "contains", "confidence": "EXTRACTED", "source_file": "C:\\Users\\allio\\Desktop\\runique\\runique\\tests\\migration\\test_column_def_extra.rs", "source_location": "L225", "weight": 1.0}, {"source": "c_users_allio_desktop_runique_runique_tests_migration_test_column_def_extra_rs", "target": "test_column_def_extra_test_to_form_field_char", "relation": "contains", "confidence": "EXTRACTED", "source_file": "C:\\Users\\allio\\Desktop\\runique\\runique\\tests\\migration\\test_column_def_extra.rs", "source_location": "L231", "weight": 1.0}, {"source": "c_users_allio_desktop_runique_runique_tests_migration_test_column_def_extra_rs", "target": "test_column_def_extra_test_to_form_field_enum", "relation": "contains", "confidence": "EXTRACTED", "source_file": "C:\\Users\\allio\\Desktop\\runique\\runique\\tests\\migration\\test_column_def_extra.rs", "source_location": "L237", "weight": 1.0}, {"source": "c_users_allio_desktop_runique_runique_tests_migration_test_column_def_extra_rs", "target": "test_column_def_extra_test_to_form_field_string_avec_max_len", "relation": "contains", "confidence": "EXTRACTED", "source_file": "C:\\Users\\allio\\Desktop\\runique\\runique\\tests\\migration\\test_column_def_extra.rs", "source_location": "L246", "weight": 1.0}, {"source": "c_users_allio_desktop_runique_runique_tests_migration_test_column_def_extra_rs", "target": "test_column_def_extra_test_to_form_field_email_avec_max_len", "relation": "contains", "confidence": "EXTRACTED", "source_file": "C:\\Users\\allio\\Desktop\\runique\\runique\\tests\\migration\\test_column_def_extra.rs", "source_location": "L252", "weight": 1.0}, {"source": "c_users_allio_desktop_runique_runique_tests_migration_test_column_def_extra_rs", "target": "test_column_def_extra_test_to_form_field_required_quand_non_nullable", "relation": "contains", "confidence": "EXTRACTED", "source_file": "C:\\Users\\allio\\Desktop\\runique\\runique\\tests\\migration\\test_column_def_extra.rs", "source_location": "L258", "weight": 1.0}, {"source": "c_users_allio_desktop_runique_runique_tests_migration_test_column_def_extra_rs", "target": "test_column_def_extra_test_to_form_field_optionnel_quand_nullable", "relation": "contains", "confidence": "EXTRACTED", "source_file": "C:\\Users\\allio\\Desktop\\runique\\runique\\tests\\migration\\test_column_def_extra.rs", "source_location": "L266", "weight": 1.0}, {"source": "c_users_allio_desktop_runique_runique_tests_migration_test_column_def_extra_rs", "target": "test_column_def_extra_test_format_label_simple", "relation": "contains", "confidence": "EXTRACTED", "source_file": "C:\\Users\\allio\\Desktop\\runique\\runique\\tests\\migration\\test_column_def_extra.rs", "source_location": "L277", "weight": 1.0}, {"source": "c_users_allio_desktop_runique_runique_tests_migration_test_column_def_extra_rs", "target": "test_column_def_extra_test_format_label_snake_case", "relation": "contains", "confidence": "EXTRACTED", "source_file": "C:\\Users\\allio\\Desktop\\runique\\runique\\tests\\migration\\test_column_def_extra.rs", "source_location": "L286", "weight": 1.0}, {"source": "c_users_allio_desktop_runique_runique_tests_migration_test_column_def_extra_rs", "target": "test_column_def_extra_test_format_label_triple", "relation": "contains", "confidence": "EXTRACTED", "source_file": "C:\\Users\\allio\\Desktop\\runique\\runique\\tests\\migration\\test_column_def_extra.rs", "source_location": "L295", "weight": 1.0}], "raw_calls": [{"caller_nid": "test_column_def_extra_test_column_inet", "callee": "inet", "source_file": "C:\\Users\\allio\\Desktop\\runique\\runique\\tests\\migration\\test_column_def_extra.rs", "source_location": "L14"}, {"caller_nid": "test_column_def_extra_test_column_inet", "callee": "new", "source_file": "C:\\Users\\allio\\Desktop\\runique\\runique\\tests\\migration\\test_column_def_extra.rs", "source_location": "L14"}, {"caller_nid": "test_column_def_extra_test_column_cidr", "callee": "cidr", "source_file": "C:\\Users\\allio\\Desktop\\runique\\runique\\tests\\migration\\test_column_def_extra.rs", "source_location": "L20"}, {"caller_nid": "test_column_def_extra_test_column_cidr", "callee": "new", "source_file": "C:\\Users\\allio\\Desktop\\runique\\runique\\tests\\migration\\test_column_def_extra.rs", "source_location": "L20"}, {"caller_nid": "test_column_def_extra_test_column_mac_address", "callee": "mac_address", "source_file": "C:\\Users\\allio\\Desktop\\runique\\runique\\tests\\migration\\test_column_def_extra.rs", "source_location": "L26"}, {"caller_nid": "test_column_def_extra_test_column_mac_address", "callee": "new", "source_file": "C:\\Users\\allio\\Desktop\\runique\\runique\\tests\\migration\\test_column_def_extra.rs", "source_location": "L26"}, {"caller_nid": "test_column_def_extra_test_column_interval", "callee": "interval", "source_file": "C:\\Users\\allio\\Desktop\\runique\\runique\\tests\\migration\\test_column_def_extra.rs", "source_location": "L32"}, {"caller_nid": "test_column_def_extra_test_column_interval", "callee": "new", "source_file": "C:\\Users\\allio\\Desktop\\runique\\runique\\tests\\migration\\test_column_def_extra.rs", "source_location": "L32"}, {"caller_nid": "test_column_def_extra_test_column_char", "callee": "char", "source_file": "C:\\Users\\allio\\Desktop\\runique\\runique\\tests\\migration\\test_column_def_extra.rs", "source_location": "L42"}, {"caller_nid": "test_column_def_extra_test_column_char", "callee": "new", "source_file": "C:\\Users\\allio\\Desktop\\runique\\runique\\tests\\migration\\test_column_def_extra.rs", "source_location": "L42"}, {"caller_nid": "test_column_def_extra_test_column_char_len", "callee": "char_len", "source_file": "C:\\Users\\allio\\Desktop\\runique\\runique\\tests\\migration\\test_column_def_extra.rs", "source_location": "L48"}, {"caller_nid": "test_column_def_extra_test_column_char_len", "callee": "new", "source_file": "C:\\Users\\allio\\Desktop\\runique\\runique\\tests\\migration\\test_column_def_extra.rs", "source_location": "L48"}, {"caller_nid": "test_column_def_extra_test_column_var_binary", "callee": "var_binary", "source_file": "C:\\Users\\allio\\Desktop\\runique\\runique\\tests\\migration\\test_column_def_extra.rs", "source_location": "L54"}, {"caller_nid": "test_column_def_extra_test_column_var_binary", "callee": "new", "source_file": "C:\\Users\\allio\\Desktop\\runique\\runique\\tests\\migration\\test_column_def_extra.rs", "source_location": "L54"}, {"caller_nid": "test_column_def_extra_test_column_blob", "callee": "blob", "source_file": "C:\\Users\\allio\\Desktop\\runique\\runique\\tests\\migration\\test_column_def_extra.rs", "source_location": "L60"}, {"caller_nid": "test_column_def_extra_test_column_blob", "callee": "new", "source_file": "C:\\Users\\allio\\Desktop\\runique\\runique\\tests\\migration\\test_column_def_extra.rs", "source_location": "L60"}, {"caller_nid": "test_column_def_extra_test_column_unsigned", "callee": "unsigned", "source_file": "C:\\Users\\allio\\Desktop\\runique\\runique\\tests\\migration\\test_column_def_extra.rs", "source_location": "L66"}, {"caller_nid": "test_column_def_extra_test_column_unsigned", "callee": "new", "source_file": "C:\\Users\\allio\\Desktop\\runique\\runique\\tests\\migration\\test_column_def_extra.rs", "source_location": "L66"}, {"caller_nid": "test_column_def_extra_test_column_big_unsigned", "callee": "big_unsigned", "source_file": "C:\\Users\\allio\\Desktop\\runique\\runique\\tests\\migration\\test_column_def_extra.rs", "source_location": "L72"}, {"caller_nid": "test_column_def_extra_test_column_big_unsigned", "callee": "new", "source_file": "C:\\Users\\allio\\Desktop\\runique\\runique\\tests\\migration\\test_column_def_extra.rs", "source_location": "L72"}, {"caller_nid": "test_column_def_extra_test_to_sea_column_avec_default", "callee": "default", "source_file": "C:\\Users\\allio\\Desktop\\runique\\runique\\tests\\migration\\test_column_def_extra.rs", "source_location": "L82"}, {"caller_nid": "test_column_def_extra_test_to_sea_column_avec_default", "callee": "boolean", "source_file": "C:\\Users\\allio\\Desktop\\runique\\runique\\tests\\migration\\test_column_def_extra.rs", "source_location": "L82"}, {"caller_nid": "test_column_def_extra_test_to_sea_column_avec_default", "callee": "new", "source_file": "C:\\Users\\allio\\Desktop\\runique\\runique\\tests\\migration\\test_column_def_extra.rs", "source_location": "L82"}, {"caller_nid": "test_column_def_extra_test_to_sea_column_avec_default", "callee": "Bool", "source_file": "C:\\Users\\allio\\Desktop\\runique\\runique\\tests\\migration\\test_column_def_extra.rs", "source_location": "L84"}, {"caller_nid": "test_column_def_extra_test_to_sea_column_avec_default", "callee": "Some", "source_file": "C:\\Users\\allio\\Desktop\\runique\\runique\\tests\\migration\\test_column_def_extra.rs", "source_location": "L84"}, {"caller_nid": "test_column_def_extra_test_to_sea_column_avec_default", "callee": "to_sea_column", "source_file": "C:\\Users\\allio\\Desktop\\runique\\runique\\tests\\migration\\test_column_def_extra.rs", "source_location": "L85"}, {"caller_nid": "test_column_def_extra_test_to_sea_column_nullable", "callee": "nullable", "source_file": "C:\\Users\\allio\\Desktop\\runique\\runique\\tests\\migration\\test_column_def_extra.rs", "source_location": "L90"}, {"caller_nid": "test_column_def_extra_test_to_sea_column_nullable", "callee": "text", "source_file": "C:\\Users\\allio\\Desktop\\runique\\runique\\tests\\migration\\test_column_def_extra.rs", "source_location": "L90"}, {"caller_nid": "test_column_def_extra_test_to_sea_column_nullable", "callee": "new", "source_file": "C:\\Users\\allio\\Desktop\\runique\\runique\\tests\\migration\\test_column_def_extra.rs", "source_location": "L90"}, {"caller_nid": "test_column_def_extra_test_to_sea_column_nullable", "callee": "to_sea_column", "source_file": "C:\\Users\\allio\\Desktop\\runique\\runique\\tests\\migration\\test_column_def_extra.rs", "source_location": "L91"}, {"caller_nid": "test_column_def_extra_test_to_sea_column_unique", "callee": "unique", "source_file": "C:\\Users\\allio\\Desktop\\runique\\runique\\tests\\migration\\test_column_def_extra.rs", "source_location": "L96"}, {"caller_nid": "test_column_def_extra_test_to_sea_column_unique", "callee": "string", "source_file": "C:\\Users\\allio\\Desktop\\runique\\runique\\tests\\migration\\test_column_def_extra.rs", "source_location": "L96"}, {"caller_nid": "test_column_def_extra_test_to_sea_column_unique", "callee": "new", "source_file": "C:\\Users\\allio\\Desktop\\runique\\runique\\tests\\migration\\test_column_def_extra.rs", "source_location": "L96"}, {"caller_nid": "test_column_def_extra_test_to_sea_column_unique", "callee": "to_sea_column", "source_file": "C:\\Users\\allio\\Desktop\\runique\\runique\\tests\\migration\\test_column_def_extra.rs", "source_location": "L97"}, {"caller_nid": "test_column_def_extra_test_to_form_field_password_name", "callee": "string", "source_file": "C:\\Users\\allio\\Desktop\\runique\\runique\\tests\\migration\\test_column_def_extra.rs", "source_location": "L106"}, {"caller_nid": "test_column_def_extra_test_to_form_field_password_name", "callee": "new", "source_file": "C:\\Users\\allio\\Desktop\\runique\\runique\\tests\\migration\\test_column_def_extra.rs", "source_location": "L106"}, {"caller_nid": "test_column_def_extra_test_to_form_field_password_suffixe", "callee": "string", "source_file": "C:\\Users\\allio\\Desktop\\runique\\runique\\tests\\migration\\test_column_def_extra.rs", "source_location": "L112"}, {"caller_nid": "test_column_def_extra_test_to_form_field_password_suffixe", "callee": "new", "source_file": "C:\\Users\\allio\\Desktop\\runique\\runique\\tests\\migration\\test_column_def_extra.rs", "source_location": "L112"}, {"caller_nid": "test_column_def_extra_test_to_form_field_url_name", "callee": "string", "source_file": "C:\\Users\\allio\\Desktop\\runique\\runique\\tests\\migration\\test_column_def_extra.rs", "source_location": "L118"}, {"caller_nid": "test_column_def_extra_test_to_form_field_url_name", "callee": "new", "source_file": "C:\\Users\\allio\\Desktop\\runique\\runique\\tests\\migration\\test_column_def_extra.rs", "source_location": "L118"}, {"caller_nid": "test_column_def_extra_test_to_form_field_website_name", "callee": "string", "source_file": "C:\\Users\\allio\\Desktop\\runique\\runique\\tests\\migration\\test_column_def_extra.rs", "source_location": "L124"}, {"caller_nid": "test_column_def_extra_test_to_form_field_website_name", "callee": "new", "source_file": "C:\\Users\\allio\\Desktop\\runique\\runique\\tests\\migration\\test_column_def_extra.rs", "source_location": "L124"}, {"caller_nid": "test_column_def_extra_test_to_form_field_slug_name", "callee": "string", "source_file": "C:\\Users\\allio\\Desktop\\runique\\runique\\tests\\migration\\test_column_def_extra.rs", "source_location": "L130"}, {"caller_nid": "test_column_def_extra_test_to_form_field_slug_name", "callee": "new", "source_file": "C:\\Users\\allio\\Desktop\\runique\\runique\\tests\\migration\\test_column_def_extra.rs", "source_location": "L130"}, {"caller_nid": "test_column_def_extra_test_to_form_field_color_name", "callee": "string", "source_file": "C:\\Users\\allio\\Desktop\\runique\\runique\\tests\\migration\\test_column_def_extra.rs", "source_location": "L136"}, {"caller_nid": "test_column_def_extra_test_to_form_field_color_name", "callee": "new", "source_file": "C:\\Users\\allio\\Desktop\\runique\\runique\\tests\\migration\\test_column_def_extra.rs", "source_location": "L136"}, {"caller_nid": "test_column_def_extra_test_to_form_field_ip_name", "callee": "string", "source_file": "C:\\Users\\allio\\Desktop\\runique\\runique\\tests\\migration\\test_column_def_extra.rs", "source_location": "L142"}, {"caller_nid": "test_column_def_extra_test_to_form_field_ip_name", "callee": "new", "source_file": "C:\\Users\\allio\\Desktop\\runique\\runique\\tests\\migration\\test_column_def_extra.rs", "source_location": "L142"}, {"caller_nid": "test_column_def_extra_test_to_form_field_text_description", "callee": "text", "source_file": "C:\\Users\\allio\\Desktop\\runique\\runique\\tests\\migration\\test_column_def_extra.rs", "source_location": "L148"}, {"caller_nid": "test_column_def_extra_test_to_form_field_text_description", "callee": "new", "source_file": "C:\\Users\\allio\\Desktop\\runique\\runique\\tests\\migration\\test_column_def_extra.rs", "source_location": "L148"}, {"caller_nid": "test_column_def_extra_test_to_form_field_text_bio", "callee": "text", "source_file": "C:\\Users\\allio\\Desktop\\runique\\runique\\tests\\migration\\test_column_def_extra.rs", "source_location": "L154"}, {"caller_nid": "test_column_def_extra_test_to_form_field_text_bio", "callee": "new", "source_file": "C:\\Users\\allio\\Desktop\\runique\\runique\\tests\\migration\\test_column_def_extra.rs", "source_location": "L154"}, {"caller_nid": "test_column_def_extra_test_to_form_field_text_content", "callee": "text", "source_file": "C:\\Users\\allio\\Desktop\\runique\\runique\\tests\\migration\\test_column_def_extra.rs", "source_location": "L160"}, {"caller_nid": "test_column_def_extra_test_to_form_field_text_content", "callee": "new", "source_file": "C:\\Users\\allio\\Desktop\\runique\\runique\\tests\\migration\\test_column_def_extra.rs", "source_location": "L160"}, {"caller_nid": "test_column_def_extra_test_to_form_field_text_generic", "callee": "text", "source_file": "C:\\Users\\allio\\Desktop\\runique\\runique\\tests\\migration\\test_column_def_extra.rs", "source_location": "L166"}, {"caller_nid": "test_column_def_extra_test_to_form_field_text_generic", "callee": "new", "source_file": "C:\\Users\\allio\\Desktop\\runique\\runique\\tests\\migration\\test_column_def_extra.rs", "source_location": "L166"}, {"caller_nid": "test_column_def_extra_test_to_form_field_big_integer", "callee": "big_integer", "source_file": "C:\\Users\\allio\\Desktop\\runique\\runique\\tests\\migration\\test_column_def_extra.rs", "source_location": "L172"}, {"caller_nid": "test_column_def_extra_test_to_form_field_big_integer", "callee": "new", "source_file": "C:\\Users\\allio\\Desktop\\runique\\runique\\tests\\migration\\test_column_def_extra.rs", "source_location": "L172"}, {"caller_nid": "test_column_def_extra_test_to_form_field_tiny_integer", "callee": "tiny_integer", "source_file": "C:\\Users\\allio\\Desktop\\runique\\runique\\tests\\migration\\test_column_def_extra.rs", "source_location": "L178"}, {"caller_nid": "test_column_def_extra_test_to_form_field_tiny_integer", "callee": "new", "source_file": "C:\\Users\\allio\\Desktop\\runique\\runique\\tests\\migration\\test_column_def_extra.rs", "source_location": "L178"}, {"caller_nid": "test_column_def_extra_test_to_form_field_float", "callee": "float", "source_file": "C:\\Users\\allio\\Desktop\\runique\\runique\\tests\\migration\\test_column_def_extra.rs", "source_location": "L184"}, {"caller_nid": "test_column_def_extra_test_to_form_field_float", "callee": "new", "source_file": "C:\\Users\\allio\\Desktop\\runique\\runique\\tests\\migration\\test_column_def_extra.rs", "source_location": "L184"}, {"caller_nid": "test_column_def_extra_test_to_form_field_double", "callee": "double", "source_file": "C:\\Users\\allio\\Desktop\\runique\\runique\\tests\\migration\\test_column_def_extra.rs", "source_location": "L190"}, {"caller_nid": "test_column_def_extra_test_to_form_field_double", "callee": "new", "source_file": "C:\\Users\\allio\\Desktop\\runique\\runique\\tests\\migration\\test_column_def_extra.rs", "source_location": "L190"}, {"caller_nid": "test_column_def_extra_test_to_form_field_decimal", "callee": "decimal", "source_file": "C:\\Users\\allio\\Desktop\\runique\\runique\\tests\\migration\\test_column_def_extra.rs", "source_location": "L196"}, {"caller_nid": "test_column_def_extra_test_to_form_field_decimal", "callee": "new", "source_file": "C:\\Users\\allio\\Desktop\\runique\\runique\\tests\\migration\\test_column_def_extra.rs", "source_location": "L196"}, {"caller_nid": "test_column_def_extra_test_to_form_field_date", "callee": "date", "source_file": "C:\\Users\\allio\\Desktop\\runique\\runique\\tests\\migration\\test_column_def_extra.rs", "source_location": "L202"}, {"caller_nid": "test_column_def_extra_test_to_form_field_date", "callee": "new", "source_file": "C:\\Users\\allio\\Desktop\\runique\\runique\\tests\\migration\\test_column_def_extra.rs", "source_location": "L202"}, {"caller_nid": "test_column_def_extra_test_to_form_field_time", "callee": "time", "source_file": "C:\\Users\\allio\\Desktop\\runique\\runique\\tests\\migration\\test_column_def_extra.rs", "source_location": "L208"}, {"caller_nid": "test_column_def_extra_test_to_form_field_time", "callee": "new", "source_file": "C:\\Users\\allio\\Desktop\\runique\\runique\\tests\\migration\\test_column_def_extra.rs", "source_location": "L208"}, {"caller_nid": "test_column_def_extra_test_to_form_field_datetime", "callee": "datetime", "source_file": "C:\\Users\\allio\\Desktop\\runique\\runique\\tests\\migration\\test_column_def_extra.rs", "source_location": "L214"}, {"caller_nid": "test_column_def_extra_test_to_form_field_datetime", "callee": "new", "source_file": "C:\\Users\\allio\\Desktop\\runique\\runique\\tests\\migration\\test_column_def_extra.rs", "source_location": "L214"}, {"caller_nid": "test_column_def_extra_test_to_form_field_timestamp", "callee": "timestamp", "source_file": "C:\\Users\\allio\\Desktop\\runique\\runique\\tests\\migration\\test_column_def_extra.rs", "source_location": "L220"}, {"caller_nid": "test_column_def_extra_test_to_form_field_timestamp", "callee": "new", "source_file": "C:\\Users\\allio\\Desktop\\runique\\runique\\tests\\migration\\test_column_def_extra.rs", "source_location": "L220"}, {"caller_nid": "test_column_def_extra_test_to_form_field_json_binary", "callee": "json_binary", "source_file": "C:\\Users\\allio\\Desktop\\runique\\runique\\tests\\migration\\test_column_def_extra.rs", "source_location": "L226"}, {"caller_nid": "test_column_def_extra_test_to_form_field_json_binary", "callee": "new", "source_file": "C:\\Users\\allio\\Desktop\\runique\\runique\\tests\\migration\\test_column_def_extra.rs", "source_location": "L226"}, {"caller_nid": "test_column_def_extra_test_to_form_field_char", "callee": "char_len", "source_file": "C:\\Users\\allio\\Desktop\\runique\\runique\\tests\\migration\\test_column_def_extra.rs", "source_location": "L232"}, {"caller_nid": "test_column_def_extra_test_to_form_field_char", "callee": "new", "source_file": "C:\\Users\\allio\\Desktop\\runique\\runique\\tests\\migration\\test_column_def_extra.rs", "source_location": "L232"}, {"caller_nid": "test_column_def_extra_test_to_form_field_enum", "callee": "enum_type", "source_file": "C:\\Users\\allio\\Desktop\\runique\\runique\\tests\\migration\\test_column_def_extra.rs", "source_location": "L238"}, {"caller_nid": "test_column_def_extra_test_to_form_field_enum", "callee": "new", "source_file": "C:\\Users\\allio\\Desktop\\runique\\runique\\tests\\migration\\test_column_def_extra.rs", "source_location": "L238"}, {"caller_nid": "test_column_def_extra_test_to_form_field_string_avec_max_len", "callee": "max_len", "source_file": "C:\\Users\\allio\\Desktop\\runique\\runique\\tests\\migration\\test_column_def_extra.rs", "source_location": "L247"}, {"caller_nid": "test_column_def_extra_test_to_form_field_string_avec_max_len", "callee": "string", "source_file": "C:\\Users\\allio\\Desktop\\runique\\runique\\tests\\migration\\test_column_def_extra.rs", "source_location": "L247"}, {"caller_nid": "test_column_def_extra_test_to_form_field_string_avec_max_len", "callee": "new", "source_file": "C:\\Users\\allio\\Desktop\\runique\\runique\\tests\\migration\\test_column_def_extra.rs", "source_location": "L247"}, {"caller_nid": "test_column_def_extra_test_to_form_field_email_avec_max_len", "callee": "max_len", "source_file": "C:\\Users\\allio\\Desktop\\runique\\runique\\tests\\migration\\test_column_def_extra.rs", "source_location": "L253"}, {"caller_nid": "test_column_def_extra_test_to_form_field_email_avec_max_len", "callee": "string", "source_file": "C:\\Users\\allio\\Desktop\\runique\\runique\\tests\\migration\\test_column_def_extra.rs", "source_location": "L253"}, {"caller_nid": "test_column_def_extra_test_to_form_field_email_avec_max_len", "callee": "new", "source_file": "C:\\Users\\allio\\Desktop\\runique\\runique\\tests\\migration\\test_column_def_extra.rs", "source_location": "L253"}, {"caller_nid": "test_column_def_extra_test_to_form_field_required_quand_non_nullable", "callee": "string", "source_file": "C:\\Users\\allio\\Desktop\\runique\\runique\\tests\\migration\\test_column_def_extra.rs", "source_location": "L259"}, {"caller_nid": "test_column_def_extra_test_to_form_field_required_quand_non_nullable", "callee": "new", "source_file": "C:\\Users\\allio\\Desktop\\runique\\runique\\tests\\migration\\test_column_def_extra.rs", "source_location": "L259"}, {"caller_nid": "test_column_def_extra_test_to_form_field_required_quand_non_nullable", "callee": "unwrap", "source_file": "C:\\Users\\allio\\Desktop\\runique\\runique\\tests\\migration\\test_column_def_extra.rs", "source_location": "L261"}, {"caller_nid": "test_column_def_extra_test_to_form_field_required_quand_non_nullable", "callee": "to_form_field", "source_file": "C:\\Users\\allio\\Desktop\\runique\\runique\\tests\\migration\\test_column_def_extra.rs", "source_location": "L261"}, {"caller_nid": "test_column_def_extra_test_to_form_field_optionnel_quand_nullable", "callee": "nullable", "source_file": "C:\\Users\\allio\\Desktop\\runique\\runique\\tests\\migration\\test_column_def_extra.rs", "source_location": "L267"}, {"caller_nid": "test_column_def_extra_test_to_form_field_optionnel_quand_nullable", "callee": "text", "source_file": "C:\\Users\\allio\\Desktop\\runique\\runique\\tests\\migration\\test_column_def_extra.rs", "source_location": "L267"}, {"caller_nid": "test_column_def_extra_test_to_form_field_optionnel_quand_nullable", "callee": "new", "source_file": "C:\\Users\\allio\\Desktop\\runique\\runique\\tests\\migration\\test_column_def_extra.rs", "source_location": "L267"}, {"caller_nid": "test_column_def_extra_test_to_form_field_optionnel_quand_nullable", "callee": "unwrap", "source_file": "C:\\Users\\allio\\Desktop\\runique\\runique\\tests\\migration\\test_column_def_extra.rs", "source_location": "L268"}, {"caller_nid": "test_column_def_extra_test_to_form_field_optionnel_quand_nullable", "callee": "to_form_field", "source_file": "C:\\Users\\allio\\Desktop\\runique\\runique\\tests\\migration\\test_column_def_extra.rs", "source_location": "L268"}, {"caller_nid": "test_column_def_extra_test_format_label_simple", "callee": "string", "source_file": "C:\\Users\\allio\\Desktop\\runique\\runique\\tests\\migration\\test_column_def_extra.rs", "source_location": "L278"}, {"caller_nid": "test_column_def_extra_test_format_label_simple", "callee": "new", "source_file": "C:\\Users\\allio\\Desktop\\runique\\runique\\tests\\migration\\test_column_def_extra.rs", "source_location": "L278"}, {"caller_nid": "test_column_def_extra_test_format_label_simple", "callee": "unwrap", "source_file": "C:\\Users\\allio\\Desktop\\runique\\runique\\tests\\migration\\test_column_def_extra.rs", "source_location": "L279"}, {"caller_nid": "test_column_def_extra_test_format_label_simple", "callee": "to_form_field", "source_file": "C:\\Users\\allio\\Desktop\\runique\\runique\\tests\\migration\\test_column_def_extra.rs", "source_location": "L279"}, {"caller_nid": "test_column_def_extra_test_format_label_simple", "callee": "label", "source_file": "C:\\Users\\allio\\Desktop\\runique\\runique\\tests\\migration\\test_column_def_extra.rs", "source_location": "L281"}, {"caller_nid": "test_column_def_extra_test_format_label_snake_case", "callee": "string", "source_file": "C:\\Users\\allio\\Desktop\\runique\\runique\\tests\\migration\\test_column_def_extra.rs", "source_location": "L287"}, {"caller_nid": "test_column_def_extra_test_format_label_snake_case", "callee": "new", "source_file": "C:\\Users\\allio\\Desktop\\runique\\runique\\tests\\migration\\test_column_def_extra.rs", "source_location": "L287"}, {"caller_nid": "test_column_def_extra_test_format_label_snake_case", "callee": "unwrap", "source_file": "C:\\Users\\allio\\Desktop\\runique\\runique\\tests\\migration\\test_column_def_extra.rs", "source_location": "L288"}, {"caller_nid": "test_column_def_extra_test_format_label_snake_case", "callee": "to_form_field", "source_file": "C:\\Users\\allio\\Desktop\\runique\\runique\\tests\\migration\\test_column_def_extra.rs", "source_location": "L288"}, {"caller_nid": "test_column_def_extra_test_format_label_snake_case", "callee": "label", "source_file": "C:\\Users\\allio\\Desktop\\runique\\runique\\tests\\migration\\test_column_def_extra.rs", "source_location": "L290"}, {"caller_nid": "test_column_def_extra_test_format_label_triple", "callee": "date", "source_file": "C:\\Users\\allio\\Desktop\\runique\\runique\\tests\\migration\\test_column_def_extra.rs", "source_location": "L296"}, {"caller_nid": "test_column_def_extra_test_format_label_triple", "callee": "new", "source_file": "C:\\Users\\allio\\Desktop\\runique\\runique\\tests\\migration\\test_column_def_extra.rs", "source_location": "L296"}, {"caller_nid": "test_column_def_extra_test_format_label_triple", "callee": "unwrap", "source_file": "C:\\Users\\allio\\Desktop\\runique\\runique\\tests\\migration\\test_column_def_extra.rs", "source_location": "L297"}, {"caller_nid": "test_column_def_extra_test_format_label_triple", "callee": "to_form_field", "source_file": "C:\\Users\\allio\\Desktop\\runique\\runique\\tests\\migration\\test_column_def_extra.rs", "source_location": "L297"}, {"caller_nid": "test_column_def_extra_test_format_label_triple", "callee": "label", "source_file": "C:\\Users\\allio\\Desktop\\runique\\runique\\tests\\migration\\test_column_def_extra.rs", "source_location": "L299"}]}