{"nodes": [{"id": "c_users_allio_desktop_runique_runique_src_middleware_session_session_parametre_rs", "label": "session_parametre.rs", "file_type": "code", "source_file": "C:\\Users\\allio\\Desktop\\runique\\runique\\src\\middleware\\session\\session_parametre.rs", "source_location": "L1"}, {"id": "session_parametre_sessionbackend", "label": "SessionBackend", "file_type": "code", "source_file": "C:\\Users\\allio\\Desktop\\runique\\runique\\src\\middleware\\session\\session_parametre.rs", "source_location": "L5"}, {"id": "session_parametre_sessionconfig", "label": "SessionConfig", "file_type": "code", "source_file": "C:\\Users\\allio\\Desktop\\runique\\runique\\src\\middleware\\session\\session_parametre.rs", "source_location": "L10"}, {"id": "session_parametre_sessionconfig_with_duration", "label": ".with_duration()", "file_type": "code", "source_file": "C:\\Users\\allio\\Desktop\\runique\\runique\\src\\middleware\\session\\session_parametre.rs", "source_location": "L17"}, {"id": "session_parametre_sessionconfig_default", "label": ".default()", "file_type": "code", "source_file": "C:\\Users\\allio\\Desktop\\runique\\runique\\src\\middleware\\session\\session_parametre.rs", "source_location": "L24"}], "edges": [{"source": "c_users_allio_desktop_runique_runique_src_middleware_session_session_parametre_rs", "target": "arc", "relation": "imports_from", "confidence": "EXTRACTED", "source_file": "C:\\Users\\allio\\Desktop\\runique\\runique\\src\\middleware\\session\\session_parametre.rs", "source_location": "L2", "weight": 1.0}, {"source": "c_users_allio_desktop_runique_runique_src_middleware_session_session_parametre_rs", "target": "tower_sessions", "relation": "imports_from", "confidence": "EXTRACTED", "source_file": "C:\\Users\\allio\\Desktop\\runique\\runique\\src\\middleware\\session\\session_parametre.rs", "source_location": "L3", "weight": 1.0}, {"source": "c_users_allio_desktop_runique_runique_src_middleware_session_session_parametre_rs", "target": "session_parametre_sessionbackend", "relation": "contains", "confidence": "EXTRACTED", "source_file": "C:\\Users\\allio\\Desktop\\runique\\runique\\src\\middleware\\session\\session_parametre.rs", "source_location": "L5", "weight": 1.0}, {"source": "c_users_allio_desktop_runique_runique_src_middleware_session_session_parametre_rs", "target": "session_parametre_sessionconfig", "relation": "contains", "confidence": "EXTRACTED", "source_file": "C:\\Users\\allio\\Desktop\\runique\\runique\\src\\middleware\\session\\session_parametre.rs", "source_location": "L10", "weight": 1.0}, {"source": "session_parametre_sessionconfig", "target": "session_parametre_sessionconfig_with_duration", "relation": "method", "confidence": "EXTRACTED", "source_file": "C:\\Users\\allio\\Desktop\\runique\\runique\\src\\middleware\\session\\session_parametre.rs", "source_location": "L17", "weight": 1.0}, {"source": "session_parametre_sessionconfig", "target": "session_parametre_sessionconfig_default", "relation": "method", "confidence": "EXTRACTED", "source_file": "C:\\Users\\allio\\Desktop\\runique\\runique\\src\\middleware\\session\\session_parametre.rs", "source_location": "L24", "weight": 1.0}], "raw_calls": [{"caller_nid": "session_parametre_sessionconfig_default", "callee": "seconds", "source_file": "C:\\Users\\allio\\Desktop\\runique\\runique\\src\\middleware\\session\\session_parametre.rs", "source_location": "L27"}]}