{"nodes": [{"id": "c_users_allio_desktop_runique_runique_tests_context_test_static_tera_rs", "label": "test_static_tera.rs", "file_type": "code", "source_file": "C:\\Users\\allio\\Desktop\\runique\\runique\\tests\\context\\test_static_tera.rs", "source_location": "L1"}, {"id": "test_static_tera_make_tera", "label": "make_tera()", "file_type": "code", "source_file": "C:\\Users\\allio\\Desktop\\runique\\runique\\tests\\context\\test_static_tera.rs", "source_location": "L12"}, {"id": "test_static_tera_test_mask_masque_caracteres_ascii", "label": "test_mask_masque_caracteres_ascii()", "file_type": "code", "source_file": "C:\\Users\\allio\\Desktop\\runique\\runique\\tests\\context\\test_static_tera.rs", "source_location": "L31"}, {"id": "test_static_tera_test_mask_chaine_vide", "label": "test_mask_chaine_vide()", "file_type": "code", "source_file": "C:\\Users\\allio\\Desktop\\runique\\runique\\tests\\context\\test_static_tera.rs", "source_location": "L41"}, {"id": "test_static_tera_test_mask_unicode_compte_codepoints", "label": "test_mask_unicode_compte_codepoints()", "file_type": "code", "source_file": "C:\\Users\\allio\\Desktop\\runique\\runique\\tests\\context\\test_static_tera.rs", "source_location": "L51"}, {"id": "test_static_tera_test_mask_un_seul_caractere", "label": "test_mask_un_seul_caractere()", "file_type": "code", "source_file": "C:\\Users\\allio\\Desktop\\runique\\runique\\tests\\context\\test_static_tera.rs", "source_location": "L61"}, {"id": "test_static_tera_test_csrf_field_contient_input_hidden", "label": "test_csrf_field_contient_input_hidden()", "file_type": "code", "source_file": "C:\\Users\\allio\\Desktop\\runique\\runique\\tests\\context\\test_static_tera.rs", "source_location": "L75"}, {"id": "test_static_tera_test_csrf_field_contient_nom_csrf_token", "label": "test_csrf_field_contient_nom_csrf_token()", "file_type": "code", "source_file": "C:\\Users\\allio\\Desktop\\runique\\runique\\tests\\context\\test_static_tera.rs", "source_location": "L86"}, {"id": "test_static_tera_test_csrf_field_contient_valeur_token", "label": "test_csrf_field_contient_valeur_token()", "file_type": "code", "source_file": "C:\\Users\\allio\\Desktop\\runique\\runique\\tests\\context\\test_static_tera.rs", "source_location": "L97"}, {"id": "test_static_tera_test_csrf_field_format_complet", "label": "test_csrf_field_format_complet()", "file_type": "code", "source_file": "C:\\Users\\allio\\Desktop\\runique\\runique\\tests\\context\\test_static_tera.rs", "source_location": "L108"}, {"id": "test_static_tera_test_static_filter_genere_url_correcte", "label": "test_static_filter_genere_url_correcte()", "file_type": "code", "source_file": "C:\\Users\\allio\\Desktop\\runique\\runique\\tests\\context\\test_static_tera.rs", "source_location": "L124"}, {"id": "test_static_tera_test_static_filter_fichier_avec_slash_initial", "label": "test_static_filter_fichier_avec_slash_initial()", "file_type": "code", "source_file": "C:\\Users\\allio\\Desktop\\runique\\runique\\tests\\context\\test_static_tera.rs", "source_location": "L134"}, {"id": "test_static_tera_test_static_filter_chemin_avec_sous_dossier", "label": "test_static_filter_chemin_avec_sous_dossier()", "file_type": "code", "source_file": "C:\\Users\\allio\\Desktop\\runique\\runique\\tests\\context\\test_static_tera.rs", "source_location": "L144"}, {"id": "test_static_tera_test_media_filter_genere_url_correcte", "label": "test_media_filter_genere_url_correcte()", "file_type": "code", "source_file": "C:\\Users\\allio\\Desktop\\runique\\runique\\tests\\context\\test_static_tera.rs", "source_location": "L158"}, {"id": "test_static_tera_test_runique_static_filter_genere_url_correcte", "label": "test_runique_static_filter_genere_url_correcte()", "file_type": "code", "source_file": "C:\\Users\\allio\\Desktop\\runique\\runique\\tests\\context\\test_static_tera.rs", "source_location": "L172"}, {"id": "test_static_tera_test_runique_media_filter_genere_url_correcte", "label": "test_runique_media_filter_genere_url_correcte()", "file_type": "code", "source_file": "C:\\Users\\allio\\Desktop\\runique\\runique\\tests\\context\\test_static_tera.rs", "source_location": "L187"}, {"id": "test_static_tera_test_static_base_url_trailing_slash_normalise", "label": "test_static_base_url_trailing_slash_normalise()", "file_type": "code", "source_file": "C:\\Users\\allio\\Desktop\\runique\\runique\\tests\\context\\test_static_tera.rs", "source_location": "L202"}], "edges": [{"source": "c_users_allio_desktop_runique_runique_tests_context_test_static_tera_rs", "target": "register_asset_filters", "relation": "imports_from", "confidence": "EXTRACTED", "source_file": "C:\\Users\\allio\\Desktop\\runique\\runique\\tests\\context\\test_static_tera.rs", "source_location": "L4", "weight": 1.0}, {"source": "c_users_allio_desktop_runique_runique_tests_context_test_static_tera_rs", "target": "css_token", "relation": "imports_from", "confidence": "EXTRACTED", "source_file": "C:\\Users\\allio\\Desktop\\runique\\runique\\tests\\context\\test_static_tera.rs", "source_location": "L5", "weight": 1.0}, {"source": "c_users_allio_desktop_runique_runique_tests_context_test_static_tera_rs", "target": "hashmap", "relation": "imports_from", "confidence": "EXTRACTED", "source_file": "C:\\Users\\allio\\Desktop\\runique\\runique\\tests\\context\\test_static_tera.rs", "source_location": "L6", "weight": 1.0}, {"source": "c_users_allio_desktop_runique_runique_tests_context_test_static_tera_rs", "target": "sync", "relation": "imports_from", "confidence": "EXTRACTED", "source_file": "C:\\Users\\allio\\Desktop\\runique\\runique\\tests\\context\\test_static_tera.rs", "source_location": "L7", "weight": 1.0}, {"source": "c_users_allio_desktop_runique_runique_tests_context_test_static_tera_rs", "target": "tera", "relation": "imports_from", "confidence": "EXTRACTED", "source_file": "C:\\Users\\allio\\Desktop\\runique\\runique\\tests\\context\\test_static_tera.rs", "source_location": "L8", "weight": 1.0}, {"source": "c_users_allio_desktop_runique_runique_tests_context_test_static_tera_rs", "target": "test_static_tera_make_tera", "relation": "contains", "confidence": "EXTRACTED", "source_file": "C:\\Users\\allio\\Desktop\\runique\\runique\\tests\\context\\test_static_tera.rs", "source_location": "L12", "weight": 1.0}, {"source": "c_users_allio_desktop_runique_runique_tests_context_test_static_tera_rs", "target": "test_static_tera_test_mask_masque_caracteres_ascii", "relation": "contains", "confidence": "EXTRACTED", "source_file": "C:\\Users\\allio\\Desktop\\runique\\runique\\tests\\context\\test_static_tera.rs", "source_location": "L31", "weight": 1.0}, {"source": "c_users_allio_desktop_runique_runique_tests_context_test_static_tera_rs", "target": "test_static_tera_test_mask_chaine_vide", "relation": "contains", "confidence": "EXTRACTED", "source_file": "C:\\Users\\allio\\Desktop\\runique\\runique\\tests\\context\\test_static_tera.rs", "source_location": "L41", "weight": 1.0}, {"source": "c_users_allio_desktop_runique_runique_tests_context_test_static_tera_rs", "target": "test_static_tera_test_mask_unicode_compte_codepoints", "relation": "contains", "confidence": "EXTRACTED", "source_file": "C:\\Users\\allio\\Desktop\\runique\\runique\\tests\\context\\test_static_tera.rs", "source_location": "L51", "weight": 1.0}, {"source": "c_users_allio_desktop_runique_runique_tests_context_test_static_tera_rs", "target": "test_static_tera_test_mask_un_seul_caractere", "relation": "contains", "confidence": "EXTRACTED", "source_file": "C:\\Users\\allio\\Desktop\\runique\\runique\\tests\\context\\test_static_tera.rs", "source_location": "L61", "weight": 1.0}, {"source": "c_users_allio_desktop_runique_runique_tests_context_test_static_tera_rs", "target": "test_static_tera_test_csrf_field_contient_input_hidden", "relation": "contains", "confidence": "EXTRACTED", "source_file": "C:\\Users\\allio\\Desktop\\runique\\runique\\tests\\context\\test_static_tera.rs", "source_location": "L75", "weight": 1.0}, {"source": "c_users_allio_desktop_runique_runique_tests_context_test_static_tera_rs", "target": "test_static_tera_test_csrf_field_contient_nom_csrf_token", "relation": "contains", "confidence": "EXTRACTED", "source_file": "C:\\Users\\allio\\Desktop\\runique\\runique\\tests\\context\\test_static_tera.rs", "source_location": "L86", "weight": 1.0}, {"source": "c_users_allio_desktop_runique_runique_tests_context_test_static_tera_rs", "target": "test_static_tera_test_csrf_field_contient_valeur_token", "relation": "contains", "confidence": "EXTRACTED", "source_file": "C:\\Users\\allio\\Desktop\\runique\\runique\\tests\\context\\test_static_tera.rs", "source_location": "L97", "weight": 1.0}, {"source": "c_users_allio_desktop_runique_runique_tests_context_test_static_tera_rs", "target": "test_static_tera_test_csrf_field_format_complet", "relation": "contains", "confidence": "EXTRACTED", "source_file": "C:\\Users\\allio\\Desktop\\runique\\runique\\tests\\context\\test_static_tera.rs", "source_location": "L108", "weight": 1.0}, {"source": "c_users_allio_desktop_runique_runique_tests_context_test_static_tera_rs", "target": "test_static_tera_test_static_filter_genere_url_correcte", "relation": "contains", "confidence": "EXTRACTED", "source_file": "C:\\Users\\allio\\Desktop\\runique\\runique\\tests\\context\\test_static_tera.rs", "source_location": "L124", "weight": 1.0}, {"source": "c_users_allio_desktop_runique_runique_tests_context_test_static_tera_rs", "target": "test_static_tera_test_static_filter_fichier_avec_slash_initial", "relation": "contains", "confidence": "EXTRACTED", "source_file": "C:\\Users\\allio\\Desktop\\runique\\runique\\tests\\context\\test_static_tera.rs", "source_location": "L134", "weight": 1.0}, {"source": "c_users_allio_desktop_runique_runique_tests_context_test_static_tera_rs", "target": "test_static_tera_test_static_filter_chemin_avec_sous_dossier", "relation": "contains", "confidence": "EXTRACTED", "source_file": "C:\\Users\\allio\\Desktop\\runique\\runique\\tests\\context\\test_static_tera.rs", "source_location": "L144", "weight": 1.0}, {"source": "c_users_allio_desktop_runique_runique_tests_context_test_static_tera_rs", "target": "test_static_tera_test_media_filter_genere_url_correcte", "relation": "contains", "confidence": "EXTRACTED", "source_file": "C:\\Users\\allio\\Desktop\\runique\\runique\\tests\\context\\test_static_tera.rs", "source_location": "L158", "weight": 1.0}, {"source": "c_users_allio_desktop_runique_runique_tests_context_test_static_tera_rs", "target": "test_static_tera_test_runique_static_filter_genere_url_correcte", "relation": "contains", "confidence": "EXTRACTED", "source_file": "C:\\Users\\allio\\Desktop\\runique\\runique\\tests\\context\\test_static_tera.rs", "source_location": "L172", "weight": 1.0}, {"source": "c_users_allio_desktop_runique_runique_tests_context_test_static_tera_rs", "target": "test_static_tera_test_runique_media_filter_genere_url_correcte", "relation": "contains", "confidence": "EXTRACTED", "source_file": "C:\\Users\\allio\\Desktop\\runique\\runique\\tests\\context\\test_static_tera.rs", "source_location": "L187", "weight": 1.0}, {"source": "c_users_allio_desktop_runique_runique_tests_context_test_static_tera_rs", "target": "test_static_tera_test_static_base_url_trailing_slash_normalise", "relation": "contains", "confidence": "EXTRACTED", "source_file": "C:\\Users\\allio\\Desktop\\runique\\runique\\tests\\context\\test_static_tera.rs", "source_location": "L202", "weight": 1.0}, {"source": "test_static_tera_test_mask_masque_caracteres_ascii", "target": "test_static_tera_make_tera", "relation": "calls", "confidence": "EXTRACTED", "source_file": "C:\\Users\\allio\\Desktop\\runique\\runique\\tests\\context\\test_static_tera.rs", "source_location": "L32", "weight": 1.0}, {"source": "test_static_tera_test_mask_chaine_vide", "target": "test_static_tera_make_tera", "relation": "calls", "confidence": "EXTRACTED", "source_file": "C:\\Users\\allio\\Desktop\\runique\\runique\\tests\\context\\test_static_tera.rs", "source_location": "L42", "weight": 1.0}, {"source": "test_static_tera_test_mask_unicode_compte_codepoints", "target": "test_static_tera_make_tera", "relation": "calls", "confidence": "EXTRACTED", "source_file": "C:\\Users\\allio\\Desktop\\runique\\runique\\tests\\context\\test_static_tera.rs", "source_location": "L52", "weight": 1.0}, {"source": "test_static_tera_test_mask_un_seul_caractere", "target": "test_static_tera_make_tera", "relation": "calls", "confidence": "EXTRACTED", "source_file": "C:\\Users\\allio\\Desktop\\runique\\runique\\tests\\context\\test_static_tera.rs", "source_location": "L62", "weight": 1.0}, {"source": "test_static_tera_test_csrf_field_contient_input_hidden", "target": "test_static_tera_make_tera", "relation": "calls", "confidence": "EXTRACTED", "source_file": "C:\\Users\\allio\\Desktop\\runique\\runique\\tests\\context\\test_static_tera.rs", "source_location": "L76", "weight": 1.0}, {"source": "test_static_tera_test_csrf_field_contient_nom_csrf_token", "target": "test_static_tera_make_tera", "relation": "calls", "confidence": "EXTRACTED", "source_file": "C:\\Users\\allio\\Desktop\\runique\\runique\\tests\\context\\test_static_tera.rs", "source_location": "L87", "weight": 1.0}, {"source": "test_static_tera_test_csrf_field_contient_valeur_token", "target": "test_static_tera_make_tera", "relation": "calls", "confidence": "EXTRACTED", "source_file": "C:\\Users\\allio\\Desktop\\runique\\runique\\tests\\context\\test_static_tera.rs", "source_location": "L98", "weight": 1.0}, {"source": "test_static_tera_test_csrf_field_format_complet", "target": "test_static_tera_make_tera", "relation": "calls", "confidence": "EXTRACTED", "source_file": "C:\\Users\\allio\\Desktop\\runique\\runique\\tests\\context\\test_static_tera.rs", "source_location": "L109", "weight": 1.0}, {"source": "test_static_tera_test_static_filter_genere_url_correcte", "target": "test_static_tera_make_tera", "relation": "calls", "confidence": "EXTRACTED", "source_file": "C:\\Users\\allio\\Desktop\\runique\\runique\\tests\\context\\test_static_tera.rs", "source_location": "L125", "weight": 1.0}, {"source": "test_static_tera_test_static_filter_fichier_avec_slash_initial", "target": "test_static_tera_make_tera", "relation": "calls", "confidence": "EXTRACTED", "source_file": "C:\\Users\\allio\\Desktop\\runique\\runique\\tests\\context\\test_static_tera.rs", "source_location": "L135", "weight": 1.0}, {"source": "test_static_tera_test_static_filter_chemin_avec_sous_dossier", "target": "test_static_tera_make_tera", "relation": "calls", "confidence": "EXTRACTED", "source_file": "C:\\Users\\allio\\Desktop\\runique\\runique\\tests\\context\\test_static_tera.rs", "source_location": "L145", "weight": 1.0}, {"source": "test_static_tera_test_media_filter_genere_url_correcte", "target": "test_static_tera_make_tera", "relation": "calls", "confidence": "EXTRACTED", "source_file": "C:\\Users\\allio\\Desktop\\runique\\runique\\tests\\context\\test_static_tera.rs", "source_location": "L159", "weight": 1.0}, {"source": "test_static_tera_test_runique_static_filter_genere_url_correcte", "target": "test_static_tera_make_tera", "relation": "calls", "confidence": "EXTRACTED", "source_file": "C:\\Users\\allio\\Desktop\\runique\\runique\\tests\\context\\test_static_tera.rs", "source_location": "L173", "weight": 1.0}, {"source": "test_static_tera_test_runique_media_filter_genere_url_correcte", "target": "test_static_tera_make_tera", "relation": "calls", "confidence": "EXTRACTED", "source_file": "C:\\Users\\allio\\Desktop\\runique\\runique\\tests\\context\\test_static_tera.rs", "source_location": "L188", "weight": 1.0}], "raw_calls": [{"caller_nid": "test_static_tera_make_tera", "callee": "default", "source_file": "C:\\Users\\allio\\Desktop\\runique\\runique\\tests\\context\\test_static_tera.rs", "source_location": "L13"}, {"caller_nid": "test_static_tera_make_tera", "callee": "new", "source_file": "C:\\Users\\allio\\Desktop\\runique\\runique\\tests\\context\\test_static_tera.rs", "source_location": "L14"}, {"caller_nid": "test_static_tera_make_tera", "callee": "new", "source_file": "C:\\Users\\allio\\Desktop\\runique\\runique\\tests\\context\\test_static_tera.rs", "source_location": "L14"}, {"caller_nid": "test_static_tera_make_tera", "callee": "new", "source_file": "C:\\Users\\allio\\Desktop\\runique\\runique\\tests\\context\\test_static_tera.rs", "source_location": "L14"}, {"caller_nid": "test_static_tera_make_tera", "callee": "register_asset_filters", "source_file": "C:\\Users\\allio\\Desktop\\runique\\runique\\tests\\context\\test_static_tera.rs", "source_location": "L15"}, {"caller_nid": "test_static_tera_make_tera", "callee": "to_string", "source_file": "C:\\Users\\allio\\Desktop\\runique\\runique\\tests\\context\\test_static_tera.rs", "source_location": "L17"}, {"caller_nid": "test_static_tera_make_tera", "callee": "to_string", "source_file": "C:\\Users\\allio\\Desktop\\runique\\runique\\tests\\context\\test_static_tera.rs", "source_location": "L18"}, {"caller_nid": "test_static_tera_make_tera", "callee": "to_string", "source_file": "C:\\Users\\allio\\Desktop\\runique\\runique\\tests\\context\\test_static_tera.rs", "source_location": "L19"}, {"caller_nid": "test_static_tera_make_tera", "callee": "to_string", "source_file": "C:\\Users\\allio\\Desktop\\runique\\runique\\tests\\context\\test_static_tera.rs", "source_location": "L20"}, {"caller_nid": "test_static_tera_test_mask_masque_caracteres_ascii", "callee": "unwrap", "source_file": "C:\\Users\\allio\\Desktop\\runique\\runique\\tests\\context\\test_static_tera.rs", "source_location": "L33"}, {"caller_nid": "test_static_tera_test_mask_masque_caracteres_ascii", "callee": "add_raw_template", "source_file": "C:\\Users\\allio\\Desktop\\runique\\runique\\tests\\context\\test_static_tera.rs", "source_location": "L33"}, {"caller_nid": "test_static_tera_test_mask_masque_caracteres_ascii", "callee": "new", "source_file": "C:\\Users\\allio\\Desktop\\runique\\runique\\tests\\context\\test_static_tera.rs", "source_location": "L34"}, {"caller_nid": "test_static_tera_test_mask_masque_caracteres_ascii", "callee": "insert", "source_file": "C:\\Users\\allio\\Desktop\\runique\\runique\\tests\\context\\test_static_tera.rs", "source_location": "L35"}, {"caller_nid": "test_static_tera_test_mask_masque_caracteres_ascii", "callee": "unwrap", "source_file": "C:\\Users\\allio\\Desktop\\runique\\runique\\tests\\context\\test_static_tera.rs", "source_location": "L36"}, {"caller_nid": "test_static_tera_test_mask_masque_caracteres_ascii", "callee": "render", "source_file": "C:\\Users\\allio\\Desktop\\runique\\runique\\tests\\context\\test_static_tera.rs", "source_location": "L36"}, {"caller_nid": "test_static_tera_test_mask_chaine_vide", "callee": "unwrap", "source_file": "C:\\Users\\allio\\Desktop\\runique\\runique\\tests\\context\\test_static_tera.rs", "source_location": "L43"}, {"caller_nid": "test_static_tera_test_mask_chaine_vide", "callee": "add_raw_template", "source_file": "C:\\Users\\allio\\Desktop\\runique\\runique\\tests\\context\\test_static_tera.rs", "source_location": "L43"}, {"caller_nid": "test_static_tera_test_mask_chaine_vide", "callee": "new", "source_file": "C:\\Users\\allio\\Desktop\\runique\\runique\\tests\\context\\test_static_tera.rs", "source_location": "L44"}, {"caller_nid": "test_static_tera_test_mask_chaine_vide", "callee": "insert", "source_file": "C:\\Users\\allio\\Desktop\\runique\\runique\\tests\\context\\test_static_tera.rs", "source_location": "L45"}, {"caller_nid": "test_static_tera_test_mask_chaine_vide", "callee": "unwrap", "source_file": "C:\\Users\\allio\\Desktop\\runique\\runique\\tests\\context\\test_static_tera.rs", "source_location": "L46"}, {"caller_nid": "test_static_tera_test_mask_chaine_vide", "callee": "render", "source_file": "C:\\Users\\allio\\Desktop\\runique\\runique\\tests\\context\\test_static_tera.rs", "source_location": "L46"}, {"caller_nid": "test_static_tera_test_mask_unicode_compte_codepoints", "callee": "unwrap", "source_file": "C:\\Users\\allio\\Desktop\\runique\\runique\\tests\\context\\test_static_tera.rs", "source_location": "L53"}, {"caller_nid": "test_static_tera_test_mask_unicode_compte_codepoints", "callee": "add_raw_template", "source_file": "C:\\Users\\allio\\Desktop\\runique\\runique\\tests\\context\\test_static_tera.rs", "source_location": "L53"}, {"caller_nid": "test_static_tera_test_mask_unicode_compte_codepoints", "callee": "new", "source_file": "C:\\Users\\allio\\Desktop\\runique\\runique\\tests\\context\\test_static_tera.rs", "source_location": "L54"}, {"caller_nid": "test_static_tera_test_mask_unicode_compte_codepoints", "callee": "insert", "source_file": "C:\\Users\\allio\\Desktop\\runique\\runique\\tests\\context\\test_static_tera.rs", "source_location": "L55"}, {"caller_nid": "test_static_tera_test_mask_unicode_compte_codepoints", "callee": "unwrap", "source_file": "C:\\Users\\allio\\Desktop\\runique\\runique\\tests\\context\\test_static_tera.rs", "source_location": "L56"}, {"caller_nid": "test_static_tera_test_mask_unicode_compte_codepoints", "callee": "render", "source_file": "C:\\Users\\allio\\Desktop\\runique\\runique\\tests\\context\\test_static_tera.rs", "source_location": "L56"}, {"caller_nid": "test_static_tera_test_mask_un_seul_caractere", "callee": "unwrap", "source_file": "C:\\Users\\allio\\Desktop\\runique\\runique\\tests\\context\\test_static_tera.rs", "source_location": "L63"}, {"caller_nid": "test_static_tera_test_mask_un_seul_caractere", "callee": "add_raw_template", "source_file": "C:\\Users\\allio\\Desktop\\runique\\runique\\tests\\context\\test_static_tera.rs", "source_location": "L63"}, {"caller_nid": "test_static_tera_test_mask_un_seul_caractere", "callee": "new", "source_file": "C:\\Users\\allio\\Desktop\\runique\\runique\\tests\\context\\test_static_tera.rs", "source_location": "L64"}, {"caller_nid": "test_static_tera_test_mask_un_seul_caractere", "callee": "insert", "source_file": "C:\\Users\\allio\\Desktop\\runique\\runique\\tests\\context\\test_static_tera.rs", "source_location": "L65"}, {"caller_nid": "test_static_tera_test_mask_un_seul_caractere", "callee": "unwrap", "source_file": "C:\\Users\\allio\\Desktop\\runique\\runique\\tests\\context\\test_static_tera.rs", "source_location": "L66"}, {"caller_nid": "test_static_tera_test_mask_un_seul_caractere", "callee": "render", "source_file": "C:\\Users\\allio\\Desktop\\runique\\runique\\tests\\context\\test_static_tera.rs", "source_location": "L66"}, {"caller_nid": "test_static_tera_test_csrf_field_contient_input_hidden", "callee": "unwrap", "source_file": "C:\\Users\\allio\\Desktop\\runique\\runique\\tests\\context\\test_static_tera.rs", "source_location": "L77"}, {"caller_nid": "test_static_tera_test_csrf_field_contient_input_hidden", "callee": "add_raw_template", "source_file": "C:\\Users\\allio\\Desktop\\runique\\runique\\tests\\context\\test_static_tera.rs", "source_location": "L77"}, {"caller_nid": "test_static_tera_test_csrf_field_contient_input_hidden", "callee": "new", "source_file": "C:\\Users\\allio\\Desktop\\runique\\runique\\tests\\context\\test_static_tera.rs", "source_location": "L79"}, {"caller_nid": "test_static_tera_test_csrf_field_contient_input_hidden", "callee": "insert", "source_file": "C:\\Users\\allio\\Desktop\\runique\\runique\\tests\\context\\test_static_tera.rs", "source_location": "L80"}, {"caller_nid": "test_static_tera_test_csrf_field_contient_input_hidden", "callee": "unwrap", "source_file": "C:\\Users\\allio\\Desktop\\runique\\runique\\tests\\context\\test_static_tera.rs", "source_location": "L81"}, {"caller_nid": "test_static_tera_test_csrf_field_contient_input_hidden", "callee": "render", "source_file": "C:\\Users\\allio\\Desktop\\runique\\runique\\tests\\context\\test_static_tera.rs", "source_location": "L81"}, {"caller_nid": "test_static_tera_test_csrf_field_contient_nom_csrf_token", "callee": "unwrap", "source_file": "C:\\Users\\allio\\Desktop\\runique\\runique\\tests\\context\\test_static_tera.rs", "source_location": "L88"}, {"caller_nid": "test_static_tera_test_csrf_field_contient_nom_csrf_token", "callee": "add_raw_template", "source_file": "C:\\Users\\allio\\Desktop\\runique\\runique\\tests\\context\\test_static_tera.rs", "source_location": "L88"}, {"caller_nid": "test_static_tera_test_csrf_field_contient_nom_csrf_token", "callee": "new", "source_file": "C:\\Users\\allio\\Desktop\\runique\\runique\\tests\\context\\test_static_tera.rs", "source_location": "L90"}, {"caller_nid": "test_static_tera_test_csrf_field_contient_nom_csrf_token", "callee": "insert", "source_file": "C:\\Users\\allio\\Desktop\\runique\\runique\\tests\\context\\test_static_tera.rs", "source_location": "L91"}, {"caller_nid": "test_static_tera_test_csrf_field_contient_nom_csrf_token", "callee": "unwrap", "source_file": "C:\\Users\\allio\\Desktop\\runique\\runique\\tests\\context\\test_static_tera.rs", "source_location": "L92"}, {"caller_nid": "test_static_tera_test_csrf_field_contient_nom_csrf_token", "callee": "render", "source_file": "C:\\Users\\allio\\Desktop\\runique\\runique\\tests\\context\\test_static_tera.rs", "source_location": "L92"}, {"caller_nid": "test_static_tera_test_csrf_field_contient_valeur_token", "callee": "unwrap", "source_file": "C:\\Users\\allio\\Desktop\\runique\\runique\\tests\\context\\test_static_tera.rs", "source_location": "L99"}, {"caller_nid": "test_static_tera_test_csrf_field_contient_valeur_token", "callee": "add_raw_template", "source_file": "C:\\Users\\allio\\Desktop\\runique\\runique\\tests\\context\\test_static_tera.rs", "source_location": "L99"}, {"caller_nid": "test_static_tera_test_csrf_field_contient_valeur_token", "callee": "new", "source_file": "C:\\Users\\allio\\Desktop\\runique\\runique\\tests\\context\\test_static_tera.rs", "source_location": "L101"}, {"caller_nid": "test_static_tera_test_csrf_field_contient_valeur_token", "callee": "insert", "source_file": "C:\\Users\\allio\\Desktop\\runique\\runique\\tests\\context\\test_static_tera.rs", "source_location": "L102"}, {"caller_nid": "test_static_tera_test_csrf_field_contient_valeur_token", "callee": "unwrap", "source_file": "C:\\Users\\allio\\Desktop\\runique\\runique\\tests\\context\\test_static_tera.rs", "source_location": "L103"}, {"caller_nid": "test_static_tera_test_csrf_field_contient_valeur_token", "callee": "render", "source_file": "C:\\Users\\allio\\Desktop\\runique\\runique\\tests\\context\\test_static_tera.rs", "source_location": "L103"}, {"caller_nid": "test_static_tera_test_csrf_field_format_complet", "callee": "unwrap", "source_file": "C:\\Users\\allio\\Desktop\\runique\\runique\\tests\\context\\test_static_tera.rs", "source_location": "L110"}, {"caller_nid": "test_static_tera_test_csrf_field_format_complet", "callee": "add_raw_template", "source_file": "C:\\Users\\allio\\Desktop\\runique\\runique\\tests\\context\\test_static_tera.rs", "source_location": "L110"}, {"caller_nid": "test_static_tera_test_csrf_field_format_complet", "callee": "new", "source_file": "C:\\Users\\allio\\Desktop\\runique\\runique\\tests\\context\\test_static_tera.rs", "source_location": "L112"}, {"caller_nid": "test_static_tera_test_csrf_field_format_complet", "callee": "insert", "source_file": "C:\\Users\\allio\\Desktop\\runique\\runique\\tests\\context\\test_static_tera.rs", "source_location": "L113"}, {"caller_nid": "test_static_tera_test_csrf_field_format_complet", "callee": "unwrap", "source_file": "C:\\Users\\allio\\Desktop\\runique\\runique\\tests\\context\\test_static_tera.rs", "source_location": "L114"}, {"caller_nid": "test_static_tera_test_csrf_field_format_complet", "callee": "render", "source_file": "C:\\Users\\allio\\Desktop\\runique\\runique\\tests\\context\\test_static_tera.rs", "source_location": "L114"}, {"caller_nid": "test_static_tera_test_static_filter_genere_url_correcte", "callee": "unwrap", "source_file": "C:\\Users\\allio\\Desktop\\runique\\runique\\tests\\context\\test_static_tera.rs", "source_location": "L126"}, {"caller_nid": "test_static_tera_test_static_filter_genere_url_correcte", "callee": "add_raw_template", "source_file": "C:\\Users\\allio\\Desktop\\runique\\runique\\tests\\context\\test_static_tera.rs", "source_location": "L126"}, {"caller_nid": "test_static_tera_test_static_filter_genere_url_correcte", "callee": "new", "source_file": "C:\\Users\\allio\\Desktop\\runique\\runique\\tests\\context\\test_static_tera.rs", "source_location": "L127"}, {"caller_nid": "test_static_tera_test_static_filter_genere_url_correcte", "callee": "insert", "source_file": "C:\\Users\\allio\\Desktop\\runique\\runique\\tests\\context\\test_static_tera.rs", "source_location": "L128"}, {"caller_nid": "test_static_tera_test_static_filter_genere_url_correcte", "callee": "unwrap", "source_file": "C:\\Users\\allio\\Desktop\\runique\\runique\\tests\\context\\test_static_tera.rs", "source_location": "L129"}, {"caller_nid": "test_static_tera_test_static_filter_genere_url_correcte", "callee": "render", "source_file": "C:\\Users\\allio\\Desktop\\runique\\runique\\tests\\context\\test_static_tera.rs", "source_location": "L129"}, {"caller_nid": "test_static_tera_test_static_filter_fichier_avec_slash_initial", "callee": "unwrap", "source_file": "C:\\Users\\allio\\Desktop\\runique\\runique\\tests\\context\\test_static_tera.rs", "source_location": "L136"}, {"caller_nid": "test_static_tera_test_static_filter_fichier_avec_slash_initial", "callee": "add_raw_template", "source_file": "C:\\Users\\allio\\Desktop\\runique\\runique\\tests\\context\\test_static_tera.rs", "source_location": "L136"}, {"caller_nid": "test_static_tera_test_static_filter_fichier_avec_slash_initial", "callee": "new", "source_file": "C:\\Users\\allio\\Desktop\\runique\\runique\\tests\\context\\test_static_tera.rs", "source_location": "L137"}, {"caller_nid": "test_static_tera_test_static_filter_fichier_avec_slash_initial", "callee": "insert", "source_file": "C:\\Users\\allio\\Desktop\\runique\\runique\\tests\\context\\test_static_tera.rs", "source_location": "L138"}, {"caller_nid": "test_static_tera_test_static_filter_fichier_avec_slash_initial", "callee": "unwrap", "source_file": "C:\\Users\\allio\\Desktop\\runique\\runique\\tests\\context\\test_static_tera.rs", "source_location": "L139"}, {"caller_nid": "test_static_tera_test_static_filter_fichier_avec_slash_initial", "callee": "render", "source_file": "C:\\Users\\allio\\Desktop\\runique\\runique\\tests\\context\\test_static_tera.rs", "source_location": "L139"}, {"caller_nid": "test_static_tera_test_static_filter_chemin_avec_sous_dossier", "callee": "unwrap", "source_file": "C:\\Users\\allio\\Desktop\\runique\\runique\\tests\\context\\test_static_tera.rs", "source_location": "L146"}, {"caller_nid": "test_static_tera_test_static_filter_chemin_avec_sous_dossier", "callee": "add_raw_template", "source_file": "C:\\Users\\allio\\Desktop\\runique\\runique\\tests\\context\\test_static_tera.rs", "source_location": "L146"}, {"caller_nid": "test_static_tera_test_static_filter_chemin_avec_sous_dossier", "callee": "new", "source_file": "C:\\Users\\allio\\Desktop\\runique\\runique\\tests\\context\\test_static_tera.rs", "source_location": "L147"}, {"caller_nid": "test_static_tera_test_static_filter_chemin_avec_sous_dossier", "callee": "insert", "source_file": "C:\\Users\\allio\\Desktop\\runique\\runique\\tests\\context\\test_static_tera.rs", "source_location": "L148"}, {"caller_nid": "test_static_tera_test_static_filter_chemin_avec_sous_dossier", "callee": "unwrap", "source_file": "C:\\Users\\allio\\Desktop\\runique\\runique\\tests\\context\\test_static_tera.rs", "source_location": "L149"}, {"caller_nid": "test_static_tera_test_static_filter_chemin_avec_sous_dossier", "callee": "render", "source_file": "C:\\Users\\allio\\Desktop\\runique\\runique\\tests\\context\\test_static_tera.rs", "source_location": "L149"}, {"caller_nid": "test_static_tera_test_media_filter_genere_url_correcte", "callee": "unwrap", "source_file": "C:\\Users\\allio\\Desktop\\runique\\runique\\tests\\context\\test_static_tera.rs", "source_location": "L160"}, {"caller_nid": "test_static_tera_test_media_filter_genere_url_correcte", "callee": "add_raw_template", "source_file": "C:\\Users\\allio\\Desktop\\runique\\runique\\tests\\context\\test_static_tera.rs", "source_location": "L160"}, {"caller_nid": "test_static_tera_test_media_filter_genere_url_correcte", "callee": "new", "source_file": "C:\\Users\\allio\\Desktop\\runique\\runique\\tests\\context\\test_static_tera.rs", "source_location": "L161"}, {"caller_nid": "test_static_tera_test_media_filter_genere_url_correcte", "callee": "insert", "source_file": "C:\\Users\\allio\\Desktop\\runique\\runique\\tests\\context\\test_static_tera.rs", "source_location": "L162"}, {"caller_nid": "test_static_tera_test_media_filter_genere_url_correcte", "callee": "unwrap", "source_file": "C:\\Users\\allio\\Desktop\\runique\\runique\\tests\\context\\test_static_tera.rs", "source_location": "L163"}, {"caller_nid": "test_static_tera_test_media_filter_genere_url_correcte", "callee": "render", "source_file": "C:\\Users\\allio\\Desktop\\runique\\runique\\tests\\context\\test_static_tera.rs", "source_location": "L163"}, {"caller_nid": "test_static_tera_test_runique_static_filter_genere_url_correcte", "callee": "unwrap", "source_file": "C:\\Users\\allio\\Desktop\\runique\\runique\\tests\\context\\test_static_tera.rs", "source_location": "L174"}, {"caller_nid": "test_static_tera_test_runique_static_filter_genere_url_correcte", "callee": "add_raw_template", "source_file": "C:\\Users\\allio\\Desktop\\runique\\runique\\tests\\context\\test_static_tera.rs", "source_location": "L174"}, {"caller_nid": "test_static_tera_test_runique_static_filter_genere_url_correcte", "callee": "new", "source_file": "C:\\Users\\allio\\Desktop\\runique\\runique\\tests\\context\\test_static_tera.rs", "source_location": "L176"}, {"caller_nid": "test_static_tera_test_runique_static_filter_genere_url_correcte", "callee": "insert", "source_file": "C:\\Users\\allio\\Desktop\\runique\\runique\\tests\\context\\test_static_tera.rs", "source_location": "L177"}, {"caller_nid": "test_static_tera_test_runique_static_filter_genere_url_correcte", "callee": "unwrap", "source_file": "C:\\Users\\allio\\Desktop\\runique\\runique\\tests\\context\\test_static_tera.rs", "source_location": "L178"}, {"caller_nid": "test_static_tera_test_runique_static_filter_genere_url_correcte", "callee": "render", "source_file": "C:\\Users\\allio\\Desktop\\runique\\runique\\tests\\context\\test_static_tera.rs", "source_location": "L178"}, {"caller_nid": "test_static_tera_test_runique_media_filter_genere_url_correcte", "callee": "unwrap", "source_file": "C:\\Users\\allio\\Desktop\\runique\\runique\\tests\\context\\test_static_tera.rs", "source_location": "L189"}, {"caller_nid": "test_static_tera_test_runique_media_filter_genere_url_correcte", "callee": "add_raw_template", "source_file": "C:\\Users\\allio\\Desktop\\runique\\runique\\tests\\context\\test_static_tera.rs", "source_location": "L189"}, {"caller_nid": "test_static_tera_test_runique_media_filter_genere_url_correcte", "callee": "new", "source_file": "C:\\Users\\allio\\Desktop\\runique\\runique\\tests\\context\\test_static_tera.rs", "source_location": "L191"}, {"caller_nid": "test_static_tera_test_runique_media_filter_genere_url_correcte", "callee": "insert", "source_file": "C:\\Users\\allio\\Desktop\\runique\\runique\\tests\\context\\test_static_tera.rs", "source_location": "L192"}, {"caller_nid": "test_static_tera_test_runique_media_filter_genere_url_correcte", "callee": "unwrap", "source_file": "C:\\Users\\allio\\Desktop\\runique\\runique\\tests\\context\\test_static_tera.rs", "source_location": "L193"}, {"caller_nid": "test_static_tera_test_runique_media_filter_genere_url_correcte", "callee": "render", "source_file": "C:\\Users\\allio\\Desktop\\runique\\runique\\tests\\context\\test_static_tera.rs", "source_location": "L193"}, {"caller_nid": "test_static_tera_test_static_base_url_trailing_slash_normalise", "callee": "default", "source_file": "C:\\Users\\allio\\Desktop\\runique\\runique\\tests\\context\\test_static_tera.rs", "source_location": "L204"}, {"caller_nid": "test_static_tera_test_static_base_url_trailing_slash_normalise", "callee": "new", "source_file": "C:\\Users\\allio\\Desktop\\runique\\runique\\tests\\context\\test_static_tera.rs", "source_location": "L205"}, {"caller_nid": "test_static_tera_test_static_base_url_trailing_slash_normalise", "callee": "new", "source_file": "C:\\Users\\allio\\Desktop\\runique\\runique\\tests\\context\\test_static_tera.rs", "source_location": "L205"}, {"caller_nid": "test_static_tera_test_static_base_url_trailing_slash_normalise", "callee": "new", "source_file": "C:\\Users\\allio\\Desktop\\runique\\runique\\tests\\context\\test_static_tera.rs", "source_location": "L205"}, {"caller_nid": "test_static_tera_test_static_base_url_trailing_slash_normalise", "callee": "register_asset_filters", "source_file": "C:\\Users\\allio\\Desktop\\runique\\runique\\tests\\context\\test_static_tera.rs", "source_location": "L206"}, {"caller_nid": "test_static_tera_test_static_base_url_trailing_slash_normalise", "callee": "to_string", "source_file": "C:\\Users\\allio\\Desktop\\runique\\runique\\tests\\context\\test_static_tera.rs", "source_location": "L208"}, {"caller_nid": "test_static_tera_test_static_base_url_trailing_slash_normalise", "callee": "to_string", "source_file": "C:\\Users\\allio\\Desktop\\runique\\runique\\tests\\context\\test_static_tera.rs", "source_location": "L209"}, {"caller_nid": "test_static_tera_test_static_base_url_trailing_slash_normalise", "callee": "to_string", "source_file": "C:\\Users\\allio\\Desktop\\runique\\runique\\tests\\context\\test_static_tera.rs", "source_location": "L210"}, {"caller_nid": "test_static_tera_test_static_base_url_trailing_slash_normalise", "callee": "to_string", "source_file": "C:\\Users\\allio\\Desktop\\runique\\runique\\tests\\context\\test_static_tera.rs", "source_location": "L211"}, {"caller_nid": "test_static_tera_test_static_base_url_trailing_slash_normalise", "callee": "unwrap", "source_file": "C:\\Users\\allio\\Desktop\\runique\\runique\\tests\\context\\test_static_tera.rs", "source_location": "L214"}, {"caller_nid": "test_static_tera_test_static_base_url_trailing_slash_normalise", "callee": "add_raw_template", "source_file": "C:\\Users\\allio\\Desktop\\runique\\runique\\tests\\context\\test_static_tera.rs", "source_location": "L214"}, {"caller_nid": "test_static_tera_test_static_base_url_trailing_slash_normalise", "callee": "new", "source_file": "C:\\Users\\allio\\Desktop\\runique\\runique\\tests\\context\\test_static_tera.rs", "source_location": "L215"}, {"caller_nid": "test_static_tera_test_static_base_url_trailing_slash_normalise", "callee": "insert", "source_file": "C:\\Users\\allio\\Desktop\\runique\\runique\\tests\\context\\test_static_tera.rs", "source_location": "L216"}, {"caller_nid": "test_static_tera_test_static_base_url_trailing_slash_normalise", "callee": "unwrap", "source_file": "C:\\Users\\allio\\Desktop\\runique\\runique\\tests\\context\\test_static_tera.rs", "source_location": "L217"}, {"caller_nid": "test_static_tera_test_static_base_url_trailing_slash_normalise", "callee": "render", "source_file": "C:\\Users\\allio\\Desktop\\runique\\runique\\tests\\context\\test_static_tera.rs", "source_location": "L217"}]}