{"nodes": [{"id": "c_users_allio_desktop_runique_runique_src_app_error_build_rs", "label": "error_build.rs", "file_type": "code", "source_file": "C:\\Users\\allio\\Desktop\\runique\\runique\\src\\app\\error_build.rs", "source_location": "L1"}, {"id": "error_build_builderror", "label": "BuildError", "file_type": "code", "source_file": "C:\\Users\\allio\\Desktop\\runique\\runique\\src\\app\\error_build.rs", "source_location": "L6"}, {"id": "error_build_builderrorkind", "label": "BuildErrorKind", "file_type": "code", "source_file": "C:\\Users\\allio\\Desktop\\runique\\runique\\src\\app\\error_build.rs", "source_location": "L13"}, {"id": "error_build_checkreport", "label": "CheckReport", "file_type": "code", "source_file": "C:\\Users\\allio\\Desktop\\runique\\runique\\src\\app\\error_build.rs", "source_location": "L32"}, {"id": "error_build_checkerror", "label": "CheckError", "file_type": "code", "source_file": "C:\\Users\\allio\\Desktop\\runique\\runique\\src\\app\\error_build.rs", "source_location": "L38"}, {"id": "error_build_builderror_validation", "label": ".validation()", "file_type": "code", "source_file": "C:\\Users\\allio\\Desktop\\runique\\runique\\src\\app\\error_build.rs", "source_location": "L55"}, {"id": "error_build_builderror_check", "label": ".check()", "file_type": "code", "source_file": "C:\\Users\\allio\\Desktop\\runique\\runique\\src\\app\\error_build.rs", "source_location": "L63"}, {"id": "error_build_builderror_template", "label": ".template()", "file_type": "code", "source_file": "C:\\Users\\allio\\Desktop\\runique\\runique\\src\\app\\error_build.rs", "source_location": "L71"}, {"id": "error_build_builderror_database_missing", "label": ".database_missing()", "file_type": "code", "source_file": "C:\\Users\\allio\\Desktop\\runique\\runique\\src\\app\\error_build.rs", "source_location": "L79"}, {"id": "error_build_builderror_with_context", "label": ".with_context()", "file_type": "code", "source_file": "C:\\Users\\allio\\Desktop\\runique\\runique\\src\\app\\error_build.rs", "source_location": "L87"}, {"id": "error_build_checkreport_new", "label": ".new()", "file_type": "code", "source_file": "C:\\Users\\allio\\Desktop\\runique\\runique\\src\\app\\error_build.rs", "source_location": "L95"}, {"id": "error_build_checkreport_add", "label": ".add()", "file_type": "code", "source_file": "C:\\Users\\allio\\Desktop\\runique\\runique\\src\\app\\error_build.rs", "source_location": "L100"}, {"id": "error_build_checkreport_has_errors", "label": ".has_errors()", "file_type": "code", "source_file": "C:\\Users\\allio\\Desktop\\runique\\runique\\src\\app\\error_build.rs", "source_location": "L105"}, {"id": "error_build_checkreport_count", "label": ".count()", "file_type": "code", "source_file": "C:\\Users\\allio\\Desktop\\runique\\runique\\src\\app\\error_build.rs", "source_location": "L110"}, {"id": "error_build_checkreport_default", "label": ".default()", "file_type": "code", "source_file": "C:\\Users\\allio\\Desktop\\runique\\runique\\src\\app\\error_build.rs", "source_location": "L116"}, {"id": "error_build_checkerror_new", "label": ".new()", "file_type": "code", "source_file": "C:\\Users\\allio\\Desktop\\runique\\runique\\src\\app\\error_build.rs", "source_location": "L123"}, {"id": "error_build_checkerror_with_suggestion", "label": ".with_suggestion()", "file_type": "code", "source_file": "C:\\Users\\allio\\Desktop\\runique\\runique\\src\\app\\error_build.rs", "source_location": "L132"}, {"id": "error_build_builderror_fmt", "label": ".fmt()", "file_type": "code", "source_file": "C:\\Users\\allio\\Desktop\\runique\\runique\\src\\app\\error_build.rs", "source_location": "L143"}, {"id": "error_build_checkerror_fmt", "label": ".fmt()", "file_type": "code", "source_file": "C:\\Users\\allio\\Desktop\\runique\\runique\\src\\app\\error_build.rs", "source_location": "L190"}, {"id": "error_build_builderror_from", "label": ".from()", "file_type": "code", "source_file": "C:\\Users\\allio\\Desktop\\runique\\runique\\src\\app\\error_build.rs", "source_location": "L207"}], "edges": [{"source": "c_users_allio_desktop_runique_runique_src_app_error_build_rs", "target": "fmt", "relation": "imports_from", "confidence": "EXTRACTED", "source_file": "C:\\Users\\allio\\Desktop\\runique\\runique\\src\\app\\error_build.rs", "source_location": "L2", "weight": 1.0}, {"source": "c_users_allio_desktop_runique_runique_src_app_error_build_rs", "target": "error_build_builderror", "relation": "contains", "confidence": "EXTRACTED", "source_file": "C:\\Users\\allio\\Desktop\\runique\\runique\\src\\app\\error_build.rs", "source_location": "L6", "weight": 1.0}, {"source": "c_users_allio_desktop_runique_runique_src_app_error_build_rs", "target": "error_build_builderrorkind", "relation": "contains", "confidence": "EXTRACTED", "source_file": "C:\\Users\\allio\\Desktop\\runique\\runique\\src\\app\\error_build.rs", "source_location": "L13", "weight": 1.0}, {"source": "c_users_allio_desktop_runique_runique_src_app_error_build_rs", "target": "error_build_checkreport", "relation": "contains", "confidence": "EXTRACTED", "source_file": "C:\\Users\\allio\\Desktop\\runique\\runique\\src\\app\\error_build.rs", "source_location": "L32", "weight": 1.0}, {"source": "c_users_allio_desktop_runique_runique_src_app_error_build_rs", "target": "error_build_checkerror", "relation": "contains", "confidence": "EXTRACTED", "source_file": "C:\\Users\\allio\\Desktop\\runique\\runique\\src\\app\\error_build.rs", "source_location": "L38", "weight": 1.0}, {"source": "error_build_builderror", "target": "error_build_builderror_validation", "relation": "method", "confidence": "EXTRACTED", "source_file": "C:\\Users\\allio\\Desktop\\runique\\runique\\src\\app\\error_build.rs", "source_location": "L55", "weight": 1.0}, {"source": "error_build_builderror", "target": "error_build_builderror_check", "relation": "method", "confidence": "EXTRACTED", "source_file": "C:\\Users\\allio\\Desktop\\runique\\runique\\src\\app\\error_build.rs", "source_location": "L63", "weight": 1.0}, {"source": "error_build_builderror", "target": "error_build_builderror_template", "relation": "method", "confidence": "EXTRACTED", "source_file": "C:\\Users\\allio\\Desktop\\runique\\runique\\src\\app\\error_build.rs", "source_location": "L71", "weight": 1.0}, {"source": "error_build_builderror", "target": "error_build_builderror_database_missing", "relation": "method", "confidence": "EXTRACTED", "source_file": "C:\\Users\\allio\\Desktop\\runique\\runique\\src\\app\\error_build.rs", "source_location": "L79", "weight": 1.0}, {"source": "error_build_builderror", "target": "error_build_builderror_with_context", "relation": "method", "confidence": "EXTRACTED", "source_file": "C:\\Users\\allio\\Desktop\\runique\\runique\\src\\app\\error_build.rs", "source_location": "L87", "weight": 1.0}, {"source": "error_build_checkreport", "target": "error_build_checkreport_new", "relation": "method", "confidence": "EXTRACTED", "source_file": "C:\\Users\\allio\\Desktop\\runique\\runique\\src\\app\\error_build.rs", "source_location": "L95", "weight": 1.0}, {"source": "error_build_checkreport", "target": "error_build_checkreport_add", "relation": "method", "confidence": "EXTRACTED", "source_file": "C:\\Users\\allio\\Desktop\\runique\\runique\\src\\app\\error_build.rs", "source_location": "L100", "weight": 1.0}, {"source": "error_build_checkreport", "target": "error_build_checkreport_has_errors", "relation": "method", "confidence": "EXTRACTED", "source_file": "C:\\Users\\allio\\Desktop\\runique\\runique\\src\\app\\error_build.rs", "source_location": "L105", "weight": 1.0}, {"source": "error_build_checkreport", "target": "error_build_checkreport_count", "relation": "method", "confidence": "EXTRACTED", "source_file": "C:\\Users\\allio\\Desktop\\runique\\runique\\src\\app\\error_build.rs", "source_location": "L110", "weight": 1.0}, {"source": "error_build_checkreport", "target": "error_build_checkreport_default", "relation": "method", "confidence": "EXTRACTED", "source_file": "C:\\Users\\allio\\Desktop\\runique\\runique\\src\\app\\error_build.rs", "source_location": "L116", "weight": 1.0}, {"source": "error_build_checkerror", "target": "error_build_checkerror_new", "relation": "method", "confidence": "EXTRACTED", "source_file": "C:\\Users\\allio\\Desktop\\runique\\runique\\src\\app\\error_build.rs", "source_location": "L123", "weight": 1.0}, {"source": "error_build_checkerror", "target": "error_build_checkerror_with_suggestion", "relation": "method", "confidence": "EXTRACTED", "source_file": "C:\\Users\\allio\\Desktop\\runique\\runique\\src\\app\\error_build.rs", "source_location": "L132", "weight": 1.0}, {"source": "error_build_builderror", "target": "error_build_builderror_fmt", "relation": "method", "confidence": "EXTRACTED", "source_file": "C:\\Users\\allio\\Desktop\\runique\\runique\\src\\app\\error_build.rs", "source_location": "L143", "weight": 1.0}, {"source": "error_build_checkerror", "target": "error_build_checkerror_fmt", "relation": "method", "confidence": "EXTRACTED", "source_file": "C:\\Users\\allio\\Desktop\\runique\\runique\\src\\app\\error_build.rs", "source_location": "L190", "weight": 1.0}, {"source": "error_build_builderror", "target": "error_build_builderror_from", "relation": "method", "confidence": "EXTRACTED", "source_file": "C:\\Users\\allio\\Desktop\\runique\\runique\\src\\app\\error_build.rs", "source_location": "L207", "weight": 1.0}, {"source": "error_build_checkreport_new", "target": "error_build_checkerror_new", "relation": "calls", "confidence": "EXTRACTED", "source_file": "C:\\Users\\allio\\Desktop\\runique\\runique\\src\\app\\error_build.rs", "source_location": "L96", "weight": 1.0}, {"source": "error_build_checkreport_default", "target": "error_build_checkerror_new", "relation": "calls", "confidence": "EXTRACTED", "source_file": "C:\\Users\\allio\\Desktop\\runique\\runique\\src\\app\\error_build.rs", "source_location": "L117", "weight": 1.0}, {"source": "error_build_builderror_from", "target": "error_build_builderror_template", "relation": "calls", "confidence": "EXTRACTED", "source_file": "C:\\Users\\allio\\Desktop\\runique\\runique\\src\\app\\error_build.rs", "source_location": "L208", "weight": 1.0}], "raw_calls": [{"caller_nid": "error_build_builderror_validation", "callee": "ValidationFailed", "source_file": "C:\\Users\\allio\\Desktop\\runique\\runique\\src\\app\\error_build.rs", "source_location": "L57"}, {"caller_nid": "error_build_builderror_validation", "callee": "into", "source_file": "C:\\Users\\allio\\Desktop\\runique\\runique\\src\\app\\error_build.rs", "source_location": "L57"}, {"caller_nid": "error_build_builderror_check", "callee": "CheckFailed", "source_file": "C:\\Users\\allio\\Desktop\\runique\\runique\\src\\app\\error_build.rs", "source_location": "L65"}, {"caller_nid": "error_build_builderror_template", "callee": "TemplateLoadFailed", "source_file": "C:\\Users\\allio\\Desktop\\runique\\runique\\src\\app\\error_build.rs", "source_location": "L73"}, {"caller_nid": "error_build_builderror_template", "callee": "into", "source_file": "C:\\Users\\allio\\Desktop\\runique\\runique\\src\\app\\error_build.rs", "source_location": "L73"}, {"caller_nid": "error_build_builderror_with_context", "callee": "Some", "source_file": "C:\\Users\\allio\\Desktop\\runique\\runique\\src\\app\\error_build.rs", "source_location": "L88"}, {"caller_nid": "error_build_builderror_with_context", "callee": "into", "source_file": "C:\\Users\\allio\\Desktop\\runique\\runique\\src\\app\\error_build.rs", "source_location": "L88"}, {"caller_nid": "error_build_checkreport_add", "callee": "push", "source_file": "C:\\Users\\allio\\Desktop\\runique\\runique\\src\\app\\error_build.rs", "source_location": "L101"}, {"caller_nid": "error_build_checkreport_has_errors", "callee": "is_empty", "source_file": "C:\\Users\\allio\\Desktop\\runique\\runique\\src\\app\\error_build.rs", "source_location": "L106"}, {"caller_nid": "error_build_checkreport_count", "callee": "len", "source_file": "C:\\Users\\allio\\Desktop\\runique\\runique\\src\\app\\error_build.rs", "source_location": "L111"}, {"caller_nid": "error_build_checkerror_new", "callee": "into", "source_file": "C:\\Users\\allio\\Desktop\\runique\\runique\\src\\app\\error_build.rs", "source_location": "L125"}, {"caller_nid": "error_build_checkerror_new", "callee": "into", "source_file": "C:\\Users\\allio\\Desktop\\runique\\runique\\src\\app\\error_build.rs", "source_location": "L126"}, {"caller_nid": "error_build_checkerror_with_suggestion", "callee": "Some", "source_file": "C:\\Users\\allio\\Desktop\\runique\\runique\\src\\app\\error_build.rs", "source_location": "L133"}, {"caller_nid": "error_build_checkerror_with_suggestion", "callee": "into", "source_file": "C:\\Users\\allio\\Desktop\\runique\\runique\\src\\app\\error_build.rs", "source_location": "L133"}, {"caller_nid": "error_build_builderror_fmt", "callee": "enumerate", "source_file": "C:\\Users\\allio\\Desktop\\runique\\runique\\src\\app\\error_build.rs", "source_location": "L151"}, {"caller_nid": "error_build_builderror_fmt", "callee": "iter", "source_file": "C:\\Users\\allio\\Desktop\\runique\\runique\\src\\app\\error_build.rs", "source_location": "L151"}, {"caller_nid": "error_build_builderror_fmt", "callee": "saturating_sub", "source_file": "C:\\Users\\allio\\Desktop\\runique\\runique\\src\\app\\error_build.rs", "source_location": "L162"}, {"caller_nid": "error_build_builderror_fmt", "callee": "len", "source_file": "C:\\Users\\allio\\Desktop\\runique\\runique\\src\\app\\error_build.rs", "source_location": "L162"}, {"caller_nid": "error_build_builderror_fmt", "callee": "Ok", "source_file": "C:\\Users\\allio\\Desktop\\runique\\runique\\src\\app\\error_build.rs", "source_location": "L185"}, {"caller_nid": "error_build_checkerror_fmt", "callee": "Ok", "source_file": "C:\\Users\\allio\\Desktop\\runique\\runique\\src\\app\\error_build.rs", "source_location": "L195"}, {"caller_nid": "error_build_builderror_from", "callee": "to_string", "source_file": "C:\\Users\\allio\\Desktop\\runique\\runique\\src\\app\\error_build.rs", "source_location": "L208"}]}